{"content": [[{"Unnamed: 0": 3870338, "mapped_veh_id": 147, "timestamps_UTC": "2023-09-02 02:36:23", "lat": 51.0358195, "lon": 3.7113291, "RS_E_InAirTemp_PC1": 37.0, "RS_E_InAirTemp_PC2": 35.0, "RS_E_OilPress_PC1": 251.0, "RS_E_OilPress_PC2": 258.0, "RS_E_RPM_PC1": 805.0, "RS_E_RPM_PC2": 810.0, "RS_E_WatTemp_PC1": 79.0, "RS_E_WatTemp_PC2": 78.0, "RS_T_OilTemp_PC1": 75.0, "RS_T_OilTemp_PC2": 77.0, "month": 9}, {"Unnamed: 0": 14284077, "mapped_veh_id": 147, "timestamps_UTC": "2023-09-02 02:37:23", "lat": 51.0362269, "lon": 3.7095471, "RS_E_InAirTemp_PC1": 37.0, "RS_E_InAirTemp_PC2": 35.0, "RS_E_OilPress_PC1": 248.0, "RS_E_OilPress_PC2": 255.0, "RS_E_RPM_PC1": 792.0, "RS_E_RPM_PC2": 801.0, "RS_E_WatTemp_PC1": 80.0, "RS_E_WatTemp_PC2": 79.0, "RS_T_OilTemp_PC1": 76.0, "RS_T_OilTemp_PC2": 79.0, "month": 9}, {"Unnamed: 0": 5831356, "mapped_veh_id": 147, "timestamps_UTC": "2023-09-02 02:38:23", "lat": 51.0369367, "lon": 3.7048857, "RS_E_InAirTemp_PC1": 37.0, "RS_E_InAirTemp_PC2": 35.0, "RS_E_OilPress_PC1": 248.0, "RS_E_OilPress_PC2": 251.0, "RS_E_RPM_PC1": 795.0, "RS_E_RPM_PC2": 797.0, "RS_E_WatTemp_PC1": 80.0, "RS_E_WatTemp_PC2": 79.0, "RS_T_OilTemp_PC1": 76.0, "RS_T_OilTemp_PC2": 78.0, "month": 9}, {"Unnamed: 0": 14309016, "mapped_veh_id": 147, "timestamps_UTC": "2023-09-02 02:39:23", "lat": 51.0384027, "lon": 3.6995538, "RS_E_InAirTemp_PC1": 37.0, "RS_E_InAirTemp_PC2": 35.0, "RS_E_OilPress_PC1": 317.0, "RS_E_OilPress_PC2": 258.0, "RS_E_RPM_PC1": 961.0, "RS_E_RPM_PC2": 855.0, "RS_E_WatTemp_PC1": 80.0, "RS_E_WatTemp_PC2": 78.0, "RS_T_OilTemp_PC1": 76.0, "RS_T_OilTemp_PC2": 77.0, "month": 9}, {"Unnamed: 0": 15990020, "mapped_veh_id": 147, "timestamps_UTC": "2023-09-02 02:40:24", "lat": 51.0394482, "lon": 3.6959062, "RS_E_InAirTemp_PC1": 37.0, "RS_E_InAirTemp_PC2": 35.0, "RS_E_OilPress_PC1": 244.0, "RS_E_OilPress_PC2": 255.0, "RS_E_RPM_PC1": 786.0, "RS_E_RPM_PC2": 811.0, "RS_E_WatTemp_PC1": 79.0, "RS_E_WatTemp_PC2": 78.0, "RS_T_OilTemp_PC1": 74.0, "RS_T_OilTemp_PC2": 79.0, "month": 9}, {"Unnamed: 0": 6537432, "mapped_veh_id": 147, "timestamps_UTC": "2023-09-02 02:40:54", "lat": 51.0397014, "lon": 3.6947161, "RS_E_InAirTemp_PC1": 37.0, "RS_E_InAirTemp_PC2": 35.0, "RS_E_OilPress_PC1": 124.0, "RS_E_OilPress_PC2": 158.0, "RS_E_RPM_PC1": 229.0, "RS_E_RPM_PC2": 354.0, "RS_E_WatTemp_PC1": 79.0, "RS_E_WatTemp_PC2": 78.0, "RS_T_OilTemp_PC1": 76.0, "RS_T_OilTemp_PC2": 79.0, "month": 9}, {"Unnamed: 0": 11043931, "mapped_veh_id": 147, "timestamps_UTC": "2023-09-02 02:41:27", "lat": 51.0397008, "lon": 3.6947121, "RS_E_InAirTemp_PC1": 42.0, "RS_E_InAirTemp_PC2": 38.0, "RS_E_OilPress_PC1": 6.0, "RS_E_OilPress_PC2": 3.0, "RS_E_RPM_PC1": 0.0, "RS_E_RPM_PC2": 0.0, "RS_E_WatTemp_PC1": 79.0, "RS_E_WatTemp_PC2": 78.0, "RS_T_OilTemp_PC1": 76.0, "RS_T_OilTemp_PC2": 78.0, "month": 9}, {"Unnamed: 0": 15427206, "mapped_veh_id": 147, "timestamps_UTC": "2023-09-02 02:42:26", "lat": 51.0397005, "lon": 3.6947061, "RS_E_InAirTemp_PC1": 48.0, "RS_E_InAirTemp_PC2": 45.0, "RS_E_OilPress_PC1": 3.0, "RS_E_OilPress_PC2": 3.0, "RS_E_RPM_PC1": 0.0, "RS_E_RPM_PC2": 0.0, "RS_E_WatTemp_PC1": 78.0, "RS_E_WatTemp_PC2": 78.0, "RS_T_OilTemp_PC1": 74.0, "RS_T_OilTemp_PC2": 77.0, "month": 9}, {"Unnamed: 0": 14303905, "mapped_veh_id": 147, "timestamps_UTC": "2023-09-02 02:43:27", "lat": 51.0397109, "lon": 3.694703, "RS_E_InAirTemp_PC1": 51.0, "RS_E_InAirTemp_PC2": 48.0, "RS_E_OilPress_PC1": 3.0, "RS_E_OilPress_PC2": 3.0, "RS_E_RPM_PC1": 0.0, "RS_E_RPM_PC2": 0.0, "RS_E_WatTemp_PC1": 0.0, "RS_E_WatTemp_PC2": 77.0, "RS_T_OilTemp_PC1": 74.0, "RS_T_OilTemp_PC2": 77.0, "month": 9}, {"Unnamed: 0": 16966486, "mapped_veh_id": 147, "timestamps_UTC": "2023-09-02 02:44:27", "lat": 51.0397124, "lon": 3.6947162, "RS_E_InAirTemp_PC1": 0.0, "RS_E_InAirTemp_PC2": 50.0, "RS_E_OilPress_PC1": 3.0, "RS_E_OilPress_PC2": 3.0, "RS_E_RPM_PC1": 0.0, "RS_E_RPM_PC2": 0.0, "RS_E_WatTemp_PC1": 0.0, "RS_E_WatTemp_PC2": 77.0, "RS_T_OilTemp_PC1": 74.0, "RS_T_OilTemp_PC2": 76.0, "month": 9}, {"Unnamed: 0": 10041906, "mapped_veh_id": 147, "timestamps_UTC": "2023-09-02 02:45:27", "lat": 51.0397113, "lon": 3.6947235, "RS_E_InAirTemp_PC1": 56.0, "RS_E_InAirTemp_PC2": NaN, "RS_E_OilPress_PC1": 3.0, "RS_E_OilPress_PC2": NaN, "RS_E_RPM_PC1": 0.0, "RS_E_RPM_PC2": NaN, "RS_E_WatTemp_PC1": 77.0, "RS_E_WatTemp_PC2": NaN, "RS_T_OilTemp_PC1": 75.0, "RS_T_OilTemp_PC2": NaN, "month": 9}, {"Unnamed: 0": 289198, "mapped_veh_id": 147, "timestamps_UTC": "2023-09-02 02:46:31", "lat": 51.0397135, "lon": 3.694743, "RS_E_InAirTemp_PC1": 57.0, "RS_E_InAirTemp_PC2": NaN, "RS_E_OilPress_PC1": 3.0, "RS_E_OilPress_PC2": NaN, "RS_E_RPM_PC1": 0.0, "RS_E_RPM_PC2": NaN, "RS_E_WatTemp_PC1": 77.0, "RS_E_WatTemp_PC2": NaN, "RS_T_OilTemp_PC1": 72.0, "RS_T_OilTemp_PC2": NaN, "month": 9}, {"Unnamed: 0": 279294, "mapped_veh_id": 147, "timestamps_UTC": "2023-09-02 02:47:20", "lat": 51.0396993, "lon": 3.6947288, "RS_E_InAirTemp_PC1": 0.0, "RS_E_InAirTemp_PC2": NaN, "RS_E_OilPress_PC1": 0.0, "RS_E_OilPress_PC2": NaN, "RS_E_RPM_PC1": 0.0, "RS_E_RPM_PC2": NaN, "RS_E_WatTemp_PC1": 0.0, "RS_E_WatTemp_PC2": NaN, "RS_T_OilTemp_PC1": 74.0, "RS_T_OilTemp_PC2": NaN, "month": 9}, {"Unnamed: 0": 7667916, "mapped_veh_id": 147, "timestamps_UTC": "2023-09-02 02:48:20", "lat": 51.0397035, "lon": 3.6947181, "RS_E_InAirTemp_PC1": 0.0, "RS_E_InAirTemp_PC2": NaN, "RS_E_OilPress_PC1": 0.0, "RS_E_OilPress_PC2": NaN, "RS_E_RPM_PC1": 0.0, "RS_E_RPM_PC2": NaN, "RS_E_WatTemp_PC1": 0.0, "RS_E_WatTemp_PC2": NaN, "RS_T_OilTemp_PC1": 74.0, "RS_T_OilTemp_PC2": NaN, "month": 9}, {"Unnamed: 0": 13023447, "mapped_veh_id": 147, "timestamps_UTC": "2023-09-02 02:49:21", "lat": 51.0397057, "lon": 3.6947312, "RS_E_InAirTemp_PC1": 0.0, "RS_E_InAirTemp_PC2": NaN, "RS_E_OilPress_PC1": 0.0, "RS_E_OilPress_PC2": NaN, "RS_E_RPM_PC1": 0.0, "RS_E_RPM_PC2": NaN, "RS_E_WatTemp_PC1": 0.0, "RS_E_WatTemp_PC2": NaN, "RS_T_OilTemp_PC1": 72.0, "RS_T_OilTemp_PC2": NaN, "month": 9}, {"Unnamed: 0": 3850164, "mapped_veh_id": 147, "timestamps_UTC": "2023-09-02 02:50:21", "lat": 51.0396965, "lon": 3.6947289, "RS_E_InAirTemp_PC1": 0.0, "RS_E_InAirTemp_PC2": NaN, "RS_E_OilPress_PC1": 0.0, "RS_E_OilPress_PC2": NaN, "RS_E_RPM_PC1": 0.0, "RS_E_RPM_PC2": NaN, "RS_E_WatTemp_PC1": 0.0, "RS_E_WatTemp_PC2": NaN, "RS_T_OilTemp_PC1": 73.0, "RS_T_OilTemp_PC2": NaN, "month": 9}, {"Unnamed: 0": 9069521, "mapped_veh_id": 147, "timestamps_UTC": "2023-09-02 02:51:23", "lat": 51.0396857, "lon": 3.6947373, "RS_E_InAirTemp_PC1": 0.0, "RS_E_InAirTemp_PC2": NaN, "RS_E_OilPress_PC1": 0.0, "RS_E_OilPress_PC2": NaN, "RS_E_RPM_PC1": 0.0, "RS_E_RPM_PC2": NaN, "RS_E_WatTemp_PC1": 0.0, "RS_E_WatTemp_PC2": NaN, "RS_T_OilTemp_PC1": 72.0, "RS_T_OilTemp_PC2": NaN, "month": 9}, {"Unnamed: 0": 269250, "mapped_veh_id": 147, "timestamps_UTC": "2023-09-02 02:52:24", "lat": 51.0396819, "lon": 3.6947411, "RS_E_InAirTemp_PC1": 0.0, "RS_E_InAirTemp_PC2": NaN, "RS_E_OilPress_PC1": 0.0, "RS_E_OilPress_PC2": NaN, "RS_E_RPM_PC1": 0.0, "RS_E_RPM_PC2": NaN, "RS_E_WatTemp_PC1": 0.0, "RS_E_WatTemp_PC2": NaN, "RS_T_OilTemp_PC1": 72.0, "RS_T_OilTemp_PC2": NaN, "month": 9}, {"Unnamed: 0": 284102, "mapped_veh_id": 147, "timestamps_UTC": "2023-09-02 02:53:24", "lat": 51.0396882, "lon": 3.6947241, "RS_E_InAirTemp_PC1": 0.0, "RS_E_InAirTemp_PC2": NaN, "RS_E_OilPress_PC1": 0.0, "RS_E_OilPress_PC2": NaN, "RS_E_RPM_PC1": 0.0, "RS_E_RPM_PC2": NaN, "RS_E_WatTemp_PC1": 0.0, "RS_E_WatTemp_PC2": NaN, "RS_T_OilTemp_PC1": 71.0, "RS_T_OilTemp_PC2": NaN, "month": 9}, {"Unnamed: 0": 14299065, "mapped_veh_id": 147, "timestamps_UTC": "2023-09-02 02:54:24", "lat": 51.0397035, "lon": 3.6946865, "RS_E_InAirTemp_PC1": 0.0, "RS_E_InAirTemp_PC2": NaN, "RS_E_OilPress_PC1": 0.0, "RS_E_OilPress_PC2": NaN, "RS_E_RPM_PC1": 0.0, "RS_E_RPM_PC2": NaN, "RS_E_WatTemp_PC1": 0.0, "RS_E_WatTemp_PC2": NaN, "RS_T_OilTemp_PC1": 72.0, "RS_T_OilTemp_PC2": NaN, "month": 9}, {"Unnamed: 0": 546082, "mapped_veh_id": 147, "timestamps_UTC": "2023-09-02 02:55:24", "lat": 51.0396688, "lon": 3.6947013, "RS_E_InAirTemp_PC1": 0.0, "RS_E_InAirTemp_PC2": NaN, "RS_E_OilPress_PC1": 0.0, "RS_E_OilPress_PC2": NaN, "RS_E_RPM_PC1": 0.0, "RS_E_RPM_PC2": NaN, "RS_E_WatTemp_PC1": 0.0, "RS_E_WatTemp_PC2": NaN, "RS_T_OilTemp_PC1": 71.0, "RS_T_OilTemp_PC2": NaN, "month": 9}], [{"Unnamed: 0": 14284077, "mapped_veh_id": 147, "timestamps_UTC": "2023-09-02 02:37:23", "lat": 51.0362269, "lon": 3.7095471, "RS_E_InAirTemp_PC1": 37.0, "RS_E_InAirTemp_PC2": 35.0, "RS_E_OilPress_PC1": 248.0, "RS_E_OilPress_PC2": 255.0, "RS_E_RPM_PC1": 792.0, "RS_E_RPM_PC2": 801.0, "RS_E_WatTemp_PC1": 80.0, "RS_E_WatTemp_PC2": 79.0, "RS_T_OilTemp_PC1": 76.0, "RS_T_OilTemp_PC2": 79.0, "month": 9}, {"Unnamed: 0": 5831356, "mapped_veh_id": 147, "timestamps_UTC": "2023-09-02 02:38:23", "lat": 51.0369367, "lon": 3.7048857, "RS_E_InAirTemp_PC1": 37.0, "RS_E_InAirTemp_PC2": 35.0, "RS_E_OilPress_PC1": 248.0, "RS_E_OilPress_PC2": 251.0, "RS_E_RPM_PC1": 795.0, "RS_E_RPM_PC2": 797.0, "RS_E_WatTemp_PC1": 80.0, "RS_E_WatTemp_PC2": 79.0, "RS_T_OilTemp_PC1": 76.0, "RS_T_OilTemp_PC2": 78.0, "month": 9}, {"Unnamed: 0": 14309016, "mapped_veh_id": 147, "timestamps_UTC": "2023-09-02 02:39:23", "lat": 51.0384027, "lon": 3.6995538, "RS_E_InAirTemp_PC1": 37.0, "RS_E_InAirTemp_PC2": 35.0, "RS_E_OilPress_PC1": 317.0, "RS_E_OilPress_PC2": 258.0, "RS_E_RPM_PC1": 961.0, "RS_E_RPM_PC2": 855.0, "RS_E_WatTemp_PC1": 80.0, "RS_E_WatTemp_PC2": 78.0, "RS_T_OilTemp_PC1": 76.0, "RS_T_OilTemp_PC2": 77.0, "month": 9}, {"Unnamed: 0": 15990020, "mapped_veh_id": 147, "timestamps_UTC": "2023-09-02 02:40:24", "lat": 51.0394482, "lon": 3.6959062, "RS_E_InAirTemp_PC1": 37.0, "RS_E_InAirTemp_PC2": 35.0, "RS_E_OilPress_PC1": 244.0, "RS_E_OilPress_PC2": 255.0, "RS_E_RPM_PC1": 786.0, "RS_E_RPM_PC2": 811.0, "RS_E_WatTemp_PC1": 79.0, "RS_E_WatTemp_PC2": 78.0, "RS_T_OilTemp_PC1": 74.0, "RS_T_OilTemp_PC2": 79.0, "month": 9}, {"Unnamed: 0": 6537432, "mapped_veh_id": 147, "timestamps_UTC": "2023-09-02 02:40:54", "lat": 51.0397014, "lon": 3.6947161, "RS_E_InAirTemp_PC1": 37.0, "RS_E_InAirTemp_PC2": 35.0, "RS_E_OilPress_PC1": 124.0, "RS_E_OilPress_PC2": 158.0, "RS_E_RPM_PC1": 229.0, "RS_E_RPM_PC2": 354.0, "RS_E_WatTemp_PC1": 79.0, "RS_E_WatTemp_PC2": 78.0, "RS_T_OilTemp_PC1": 76.0, "RS_T_OilTemp_PC2": 79.0, "month": 9}, {"Unnamed: 0": 11043931, "mapped_veh_id": 147, "timestamps_UTC": "2023-09-02 02:41:27", "lat": 51.0397008, "lon": 3.6947121, "RS_E_InAirTemp_PC1": 42.0, "RS_E_InAirTemp_PC2": 38.0, "RS_E_OilPress_PC1": 6.0, "RS_E_OilPress_PC2": 3.0, "RS_E_RPM_PC1": 0.0, "RS_E_RPM_PC2": 0.0, "RS_E_WatTemp_PC1": 79.0, "RS_E_WatTemp_PC2": 78.0, "RS_T_OilTemp_PC1": 76.0, "RS_T_OilTemp_PC2": 78.0, "month": 9}, {"Unnamed: 0": 15427206, "mapped_veh_id": 147, "timestamps_UTC": "2023-09-02 02:42:26", "lat": 51.0397005, "lon": 3.6947061, "RS_E_InAirTemp_PC1": 48.0, "RS_E_InAirTemp_PC2": 45.0, "RS_E_OilPress_PC1": 3.0, "RS_E_OilPress_PC2": 3.0, "RS_E_RPM_PC1": 0.0, "RS_E_RPM_PC2": 0.0, "RS_E_WatTemp_PC1": 78.0, "RS_E_WatTemp_PC2": 78.0, "RS_T_OilTemp_PC1": 74.0, "RS_T_OilTemp_PC2": 77.0, "month": 9}, {"Unnamed: 0": 14303905, "mapped_veh_id": 147, "timestamps_UTC": "2023-09-02 02:43:27", "lat": 51.0397109, "lon": 3.694703, "RS_E_InAirTemp_PC1": 51.0, "RS_E_InAirTemp_PC2": 48.0, "RS_E_OilPress_PC1": 3.0, "RS_E_OilPress_PC2": 3.0, "RS_E_RPM_PC1": 0.0, "RS_E_RPM_PC2": 0.0, "RS_E_WatTemp_PC1": 0.0, "RS_E_WatTemp_PC2": 77.0, "RS_T_OilTemp_PC1": 74.0, "RS_T_OilTemp_PC2": 77.0, "month": 9}, {"Unnamed: 0": 16966486, "mapped_veh_id": 147, "timestamps_UTC": "2023-09-02 02:44:27", "lat": 51.0397124, "lon": 3.6947162, "RS_E_InAirTemp_PC1": 0.0, "RS_E_InAirTemp_PC2": 50.0, "RS_E_OilPress_PC1": 3.0, "RS_E_OilPress_PC2": 3.0, "RS_E_RPM_PC1": 0.0, "RS_E_RPM_PC2": 0.0, "RS_E_WatTemp_PC1": 0.0, "RS_E_WatTemp_PC2": 77.0, "RS_T_OilTemp_PC1": 74.0, "RS_T_OilTemp_PC2": 76.0, "month": 9}, {"Unnamed: 0": 10041906, "mapped_veh_id": 147, "timestamps_UTC": "2023-09-02 02:45:27", "lat": 51.0397113, "lon": 3.6947235, "RS_E_InAirTemp_PC1": 56.0, "RS_E_InAirTemp_PC2": NaN, "RS_E_OilPress_PC1": 3.0, "RS_E_OilPress_PC2": NaN, "RS_E_RPM_PC1": 0.0, "RS_E_RPM_PC2": NaN, "RS_E_WatTemp_PC1": 77.0, "RS_E_WatTemp_PC2": NaN, "RS_T_OilTemp_PC1": 75.0, "RS_T_OilTemp_PC2": NaN, "month": 9}, {"Unnamed: 0": 289198, "mapped_veh_id": 147, "timestamps_UTC": "2023-09-02 02:46:31", "lat": 51.0397135, "lon": 3.694743, "RS_E_InAirTemp_PC1": 57.0, "RS_E_InAirTemp_PC2": NaN, "RS_E_OilPress_PC1": 3.0, "RS_E_OilPress_PC2": NaN, "RS_E_RPM_PC1": 0.0, "RS_E_RPM_PC2": NaN, "RS_E_WatTemp_PC1": 77.0, "RS_E_WatTemp_PC2": NaN, "RS_T_OilTemp_PC1": 72.0, "RS_T_OilTemp_PC2": NaN, "month": 9}, {"Unnamed: 0": 279294, "mapped_veh_id": 147, "timestamps_UTC": "2023-09-02 02:47:20", "lat": 51.0396993, "lon": 3.6947288, "RS_E_InAirTemp_PC1": 0.0, "RS_E_InAirTemp_PC2": NaN, "RS_E_OilPress_PC1": 0.0, "RS_E_OilPress_PC2": NaN, "RS_E_RPM_PC1": 0.0, "RS_E_RPM_PC2": NaN, "RS_E_WatTemp_PC1": 0.0, "RS_E_WatTemp_PC2": NaN, "RS_T_OilTemp_PC1": 74.0, "RS_T_OilTemp_PC2": NaN, "month": 9}, {"Unnamed: 0": 7667916, "mapped_veh_id": 147, "timestamps_UTC": "2023-09-02 02:48:20", "lat": 51.0397035, "lon": 3.6947181, "RS_E_InAirTemp_PC1": 0.0, "RS_E_InAirTemp_PC2": NaN, "RS_E_OilPress_PC1": 0.0, "RS_E_OilPress_PC2": NaN, "RS_E_RPM_PC1": 0.0, "RS_E_RPM_PC2": NaN, "RS_E_WatTemp_PC1": 0.0, "RS_E_WatTemp_PC2": NaN, "RS_T_OilTemp_PC1": 74.0, "RS_T_OilTemp_PC2": NaN, "month": 9}, {"Unnamed: 0": 13023447, "mapped_veh_id": 147, "timestamps_UTC": "2023-09-02 02:49:21", "lat": 51.0397057, "lon": 3.6947312, "RS_E_InAirTemp_PC1": 0.0, "RS_E_InAirTemp_PC2": NaN, "RS_E_OilPress_PC1": 0.0, "RS_E_OilPress_PC2": NaN, "RS_E_RPM_PC1": 0.0, "RS_E_RPM_PC2": NaN, "RS_E_WatTemp_PC1": 0.0, "RS_E_WatTemp_PC2": NaN, "RS_T_OilTemp_PC1": 72.0, "RS_T_OilTemp_PC2": NaN, "month": 9}, {"Unnamed: 0": 3850164, "mapped_veh_id": 147, "timestamps_UTC": "2023-09-02 02:50:21", "lat": 51.0396965, "lon": 3.6947289, "RS_E_InAirTemp_PC1": 0.0, "RS_E_InAirTemp_PC2": NaN, "RS_E_OilPress_PC1": 0.0, "RS_E_OilPress_PC2": NaN, "RS_E_RPM_PC1": 0.0, "RS_E_RPM_PC2": NaN, "RS_E_WatTemp_PC1": 0.0, "RS_E_WatTemp_PC2": NaN, "RS_T_OilTemp_PC1": 73.0, "RS_T_OilTemp_PC2": NaN, "month": 9}, {"Unnamed: 0": 9069521, "mapped_veh_id": 147, "timestamps_UTC": "2023-09-02 02:51:23", "lat": 51.0396857, "lon": 3.6947373, "RS_E_InAirTemp_PC1": 0.0, "RS_E_InAirTemp_PC2": NaN, "RS_E_OilPress_PC1": 0.0, "RS_E_OilPress_PC2": NaN, "RS_E_RPM_PC1": 0.0, "RS_E_RPM_PC2": NaN, "RS_E_WatTemp_PC1": 0.0, "RS_E_WatTemp_PC2": NaN, "RS_T_OilTemp_PC1": 72.0, "RS_T_OilTemp_PC2": NaN, "month": 9}, {"Unnamed: 0": 269250, "mapped_veh_id": 147, "timestamps_UTC": "2023-09-02 02:52:24", "lat": 51.0396819, "lon": 3.6947411, "RS_E_InAirTemp_PC1": 0.0, "RS_E_InAirTemp_PC2": NaN, "RS_E_OilPress_PC1": 0.0, "RS_E_OilPress_PC2": NaN, "RS_E_RPM_PC1": 0.0, "RS_E_RPM_PC2": NaN, "RS_E_WatTemp_PC1": 0.0, "RS_E_WatTemp_PC2": NaN, "RS_T_OilTemp_PC1": 72.0, "RS_T_OilTemp_PC2": NaN, "month": 9}, {"Unnamed: 0": 284102, "mapped_veh_id": 147, "timestamps_UTC": "2023-09-02 02:53:24", "lat": 51.0396882, "lon": 3.6947241, "RS_E_InAirTemp_PC1": 0.0, "RS_E_InAirTemp_PC2": NaN, "RS_E_OilPress_PC1": 0.0, "RS_E_OilPress_PC2": NaN, "RS_E_RPM_PC1": 0.0, "RS_E_RPM_PC2": NaN, "RS_E_WatTemp_PC1": 0.0, "RS_E_WatTemp_PC2": NaN, "RS_T_OilTemp_PC1": 71.0, "RS_T_OilTemp_PC2": NaN, "month": 9}, {"Unnamed: 0": 14299065, "mapped_veh_id": 147, "timestamps_UTC": "2023-09-02 02:54:24", "lat": 51.0397035, "lon": 3.6946865, "RS_E_InAirTemp_PC1": 0.0, "RS_E_InAirTemp_PC2": NaN, "RS_E_OilPress_PC1": 0.0, "RS_E_OilPress_PC2": NaN, "RS_E_RPM_PC1": 0.0, "RS_E_RPM_PC2": NaN, "RS_E_WatTemp_PC1": 0.0, "RS_E_WatTemp_PC2": NaN, "RS_T_OilTemp_PC1": 72.0, "RS_T_OilTemp_PC2": NaN, "month": 9}, {"Unnamed: 0": 546082, "mapped_veh_id": 147, "timestamps_UTC": "2023-09-02 02:55:24", "lat": 51.0396688, "lon": 3.6947013, "RS_E_InAirTemp_PC1": 0.0, "RS_E_InAirTemp_PC2": NaN, "RS_E_OilPress_PC1": 0.0, "RS_E_OilPress_PC2": NaN, "RS_E_RPM_PC1": 0.0, "RS_E_RPM_PC2": NaN, "RS_E_WatTemp_PC1": 0.0, "RS_E_WatTemp_PC2": NaN, "RS_T_OilTemp_PC1": 71.0, "RS_T_OilTemp_PC2": NaN, "month": 9}, {"Unnamed: 0": 16714629, "mapped_veh_id": 147, "timestamps_UTC": "2023-09-02 02:56:27", "lat": 51.0396889, "lon": 3.6947073, "RS_E_InAirTemp_PC1": 0.0, "RS_E_InAirTemp_PC2": NaN, "RS_E_OilPress_PC1": 0.0, "RS_E_OilPress_PC2": NaN, "RS_E_RPM_PC1": 0.0, "RS_E_RPM_PC2": NaN, "RS_E_WatTemp_PC1": 0.0, "RS_E_WatTemp_PC2": NaN, "RS_T_OilTemp_PC1": 74.0, "RS_T_OilTemp_PC2": NaN, "month": 9}], [{"Unnamed: 0": 5831356, "mapped_veh_id": 147, "timestamps_UTC": "2023-09-02 02:38:23", "lat": 51.0369367, "lon": 3.7048857, "RS_E_InAirTemp_PC1": 37.0, "RS_E_InAirTemp_PC2": 35.0, "RS_E_OilPress_PC1": 248.0, "RS_E_OilPress_PC2": 251.0, "RS_E_RPM_PC1": 795.0, "RS_E_RPM_PC2": 797.0, "RS_E_WatTemp_PC1": 80.0, "RS_E_WatTemp_PC2": 79.0, "RS_T_OilTemp_PC1": 76.0, "RS_T_OilTemp_PC2": 78.0, "month": 9}, {"Unnamed: 0": 14309016, "mapped_veh_id": 147, "timestamps_UTC": "2023-09-02 02:39:23", "lat": 51.0384027, "lon": 3.6995538, "RS_E_InAirTemp_PC1": 37.0, "RS_E_InAirTemp_PC2": 35.0, "RS_E_OilPress_PC1": 317.0, "RS_E_OilPress_PC2": 258.0, "RS_E_RPM_PC1": 961.0, "RS_E_RPM_PC2": 855.0, "RS_E_WatTemp_PC1": 80.0, "RS_E_WatTemp_PC2": 78.0, "RS_T_OilTemp_PC1": 76.0, "RS_T_OilTemp_PC2": 77.0, "month": 9}, {"Unnamed: 0": 15990020, "mapped_veh_id": 147, "timestamps_UTC": "2023-09-02 02:40:24", "lat": 51.0394482, "lon": 3.6959062, "RS_E_InAirTemp_PC1": 37.0, "RS_E_InAirTemp_PC2": 35.0, "RS_E_OilPress_PC1": 244.0, "RS_E_OilPress_PC2": 255.0, "RS_E_RPM_PC1": 786.0, "RS_E_RPM_PC2": 811.0, "RS_E_WatTemp_PC1": 79.0, "RS_E_WatTemp_PC2": 78.0, "RS_T_OilTemp_PC1": 74.0, "RS_T_OilTemp_PC2": 79.0, "month": 9}, {"Unnamed: 0": 6537432, "mapped_veh_id": 147, "timestamps_UTC": "2023-09-02 02:40:54", "lat": 51.0397014, "lon": 3.6947161, "RS_E_InAirTemp_PC1": 37.0, "RS_E_InAirTemp_PC2": 35.0, "RS_E_OilPress_PC1": 124.0, "RS_E_OilPress_PC2": 158.0, "RS_E_RPM_PC1": 229.0, "RS_E_RPM_PC2": 354.0, "RS_E_WatTemp_PC1": 79.0, "RS_E_WatTemp_PC2": 78.0, "RS_T_OilTemp_PC1": 76.0, "RS_T_OilTemp_PC2": 79.0, "month": 9}, {"Unnamed: 0": 11043931, "mapped_veh_id": 147, "timestamps_UTC": "2023-09-02 02:41:27", "lat": 51.0397008, "lon": 3.6947121, "RS_E_InAirTemp_PC1": 42.0, "RS_E_InAirTemp_PC2": 38.0, "RS_E_OilPress_PC1": 6.0, "RS_E_OilPress_PC2": 3.0, "RS_E_RPM_PC1": 0.0, "RS_E_RPM_PC2": 0.0, "RS_E_WatTemp_PC1": 79.0, "RS_E_WatTemp_PC2": 78.0, "RS_T_OilTemp_PC1": 76.0, "RS_T_OilTemp_PC2": 78.0, "month": 9}, {"Unnamed: 0": 15427206, "mapped_veh_id": 147, "timestamps_UTC": "2023-09-02 02:42:26", "lat": 51.0397005, "lon": 3.6947061, "RS_E_InAirTemp_PC1": 48.0, "RS_E_InAirTemp_PC2": 45.0, "RS_E_OilPress_PC1": 3.0, "RS_E_OilPress_PC2": 3.0, "RS_E_RPM_PC1": 0.0, "RS_E_RPM_PC2": 0.0, "RS_E_WatTemp_PC1": 78.0, "RS_E_WatTemp_PC2": 78.0, "RS_T_OilTemp_PC1": 74.0, "RS_T_OilTemp_PC2": 77.0, "month": 9}, {"Unnamed: 0": 14303905, "mapped_veh_id": 147, "timestamps_UTC": "2023-09-02 02:43:27", "lat": 51.0397109, "lon": 3.694703, "RS_E_InAirTemp_PC1": 51.0, "RS_E_InAirTemp_PC2": 48.0, "RS_E_OilPress_PC1": 3.0, "RS_E_OilPress_PC2": 3.0, "RS_E_RPM_PC1": 0.0, "RS_E_RPM_PC2": 0.0, "RS_E_WatTemp_PC1": 0.0, "RS_E_WatTemp_PC2": 77.0, "RS_T_OilTemp_PC1": 74.0, "RS_T_OilTemp_PC2": 77.0, "month": 9}, {"Unnamed: 0": 16966486, "mapped_veh_id": 147, "timestamps_UTC": "2023-09-02 02:44:27", "lat": 51.0397124, "lon": 3.6947162, "RS_E_InAirTemp_PC1": 0.0, "RS_E_InAirTemp_PC2": 50.0, "RS_E_OilPress_PC1": 3.0, "RS_E_OilPress_PC2": 3.0, "RS_E_RPM_PC1": 0.0, "RS_E_RPM_PC2": 0.0, "RS_E_WatTemp_PC1": 0.0, "RS_E_WatTemp_PC2": 77.0, "RS_T_OilTemp_PC1": 74.0, "RS_T_OilTemp_PC2": 76.0, "month": 9}, {"Unnamed: 0": 10041906, "mapped_veh_id": 147, "timestamps_UTC": "2023-09-02 02:45:27", "lat": 51.0397113, "lon": 3.6947235, "RS_E_InAirTemp_PC1": 56.0, "RS_E_InAirTemp_PC2": NaN, "RS_E_OilPress_PC1": 3.0, "RS_E_OilPress_PC2": NaN, "RS_E_RPM_PC1": 0.0, "RS_E_RPM_PC2": NaN, "RS_E_WatTemp_PC1": 77.0, "RS_E_WatTemp_PC2": NaN, "RS_T_OilTemp_PC1": 75.0, "RS_T_OilTemp_PC2": NaN, "month": 9}, {"Unnamed: 0": 289198, "mapped_veh_id": 147, "timestamps_UTC": "2023-09-02 02:46:31", "lat": 51.0397135, "lon": 3.694743, "RS_E_InAirTemp_PC1": 57.0, "RS_E_InAirTemp_PC2": NaN, "RS_E_OilPress_PC1": 3.0, "RS_E_OilPress_PC2": NaN, "RS_E_RPM_PC1": 0.0, "RS_E_RPM_PC2": NaN, "RS_E_WatTemp_PC1": 77.0, "RS_E_WatTemp_PC2": NaN, "RS_T_OilTemp_PC1": 72.0, "RS_T_OilTemp_PC2": NaN, "month": 9}, {"Unnamed: 0": 279294, "mapped_veh_id": 147, "timestamps_UTC": "2023-09-02 02:47:20", "lat": 51.0396993, "lon": 3.6947288, "RS_E_InAirTemp_PC1": 0.0, "RS_E_InAirTemp_PC2": NaN, "RS_E_OilPress_PC1": 0.0, "RS_E_OilPress_PC2": NaN, "RS_E_RPM_PC1": 0.0, "RS_E_RPM_PC2": NaN, "RS_E_WatTemp_PC1": 0.0, "RS_E_WatTemp_PC2": NaN, "RS_T_OilTemp_PC1": 74.0, "RS_T_OilTemp_PC2": NaN, "month": 9}, {"Unnamed: 0": 7667916, "mapped_veh_id": 147, "timestamps_UTC": "2023-09-02 02:48:20", "lat": 51.0397035, "lon": 3.6947181, "RS_E_InAirTemp_PC1": 0.0, "RS_E_InAirTemp_PC2": NaN, "RS_E_OilPress_PC1": 0.0, "RS_E_OilPress_PC2": NaN, "RS_E_RPM_PC1": 0.0, "RS_E_RPM_PC2": NaN, "RS_E_WatTemp_PC1": 0.0, "RS_E_WatTemp_PC2": NaN, "RS_T_OilTemp_PC1": 74.0, "RS_T_OilTemp_PC2": NaN, "month": 9}, {"Unnamed: 0": 13023447, "mapped_veh_id": 147, "timestamps_UTC": "2023-09-02 02:49:21", "lat": 51.0397057, "lon": 3.6947312, "RS_E_InAirTemp_PC1": 0.0, "RS_E_InAirTemp_PC2": NaN, "RS_E_OilPress_PC1": 0.0, "RS_E_OilPress_PC2": NaN, "RS_E_RPM_PC1": 0.0, "RS_E_RPM_PC2": NaN, "RS_E_WatTemp_PC1": 0.0, "RS_E_WatTemp_PC2": NaN, "RS_T_OilTemp_PC1": 72.0, "RS_T_OilTemp_PC2": NaN, "month": 9}, {"Unnamed: 0": 3850164, "mapped_veh_id": 147, "timestamps_UTC": "2023-09-02 02:50:21", "lat": 51.0396965, "lon": 3.6947289, "RS_E_InAirTemp_PC1": 0.0, "RS_E_InAirTemp_PC2": NaN, "RS_E_OilPress_PC1": 0.0, "RS_E_OilPress_PC2": NaN, "RS_E_RPM_PC1": 0.0, "RS_E_RPM_PC2": NaN, "RS_E_WatTemp_PC1": 0.0, "RS_E_WatTemp_PC2": NaN, "RS_T_OilTemp_PC1": 73.0, "RS_T_OilTemp_PC2": NaN, "month": 9}, {"Unnamed: 0": 9069521, "mapped_veh_id": 147, "timestamps_UTC": "2023-09-02 02:51:23", "lat": 51.0396857, "lon": 3.6947373, "RS_E_InAirTemp_PC1": 0.0, "RS_E_InAirTemp_PC2": NaN, "RS_E_OilPress_PC1": 0.0, "RS_E_OilPress_PC2": NaN, "RS_E_RPM_PC1": 0.0, "RS_E_RPM_PC2": NaN, "RS_E_WatTemp_PC1": 0.0, "RS_E_WatTemp_PC2": NaN, "RS_T_OilTemp_PC1": 72.0, "RS_T_OilTemp_PC2": NaN, "month": 9}, {"Unnamed: 0": 269250, "mapped_veh_id": 147, "timestamps_UTC": "2023-09-02 02:52:24", "lat": 51.0396819, "lon": 3.6947411, "RS_E_InAirTemp_PC1": 0.0, "RS_E_InAirTemp_PC2": NaN, "RS_E_OilPress_PC1": 0.0, "RS_E_OilPress_PC2": NaN, "RS_E_RPM_PC1": 0.0, "RS_E_RPM_PC2": NaN, "RS_E_WatTemp_PC1": 0.0, "RS_E_WatTemp_PC2": NaN, "RS_T_OilTemp_PC1": 72.0, "RS_T_OilTemp_PC2": NaN, "month": 9}, {"Unnamed: 0": 284102, "mapped_veh_id": 147, "timestamps_UTC": "2023-09-02 02:53:24", "lat": 51.0396882, "lon": 3.6947241, "RS_E_InAirTemp_PC1": 0.0, "RS_E_InAirTemp_PC2": NaN, "RS_E_OilPress_PC1": 0.0, "RS_E_OilPress_PC2": NaN, "RS_E_RPM_PC1": 0.0, "RS_E_RPM_PC2": NaN, "RS_E_WatTemp_PC1": 0.0, "RS_E_WatTemp_PC2": NaN, "RS_T_OilTemp_PC1": 71.0, "RS_T_OilTemp_PC2": NaN, "month": 9}, {"Unnamed: 0": 14299065, "mapped_veh_id": 147, "timestamps_UTC": "2023-09-02 02:54:24", "lat": 51.0397035, "lon": 3.6946865, "RS_E_InAirTemp_PC1": 0.0, "RS_E_InAirTemp_PC2": NaN, "RS_E_OilPress_PC1": 0.0, "RS_E_OilPress_PC2": NaN, "RS_E_RPM_PC1": 0.0, "RS_E_RPM_PC2": NaN, "RS_E_WatTemp_PC1": 0.0, "RS_E_WatTemp_PC2": NaN, "RS_T_OilTemp_PC1": 72.0, "RS_T_OilTemp_PC2": NaN, "month": 9}, {"Unnamed: 0": 546082, "mapped_veh_id": 147, "timestamps_UTC": "2023-09-02 02:55:24", "lat": 51.0396688, "lon": 3.6947013, "RS_E_InAirTemp_PC1": 0.0, "RS_E_InAirTemp_PC2": NaN, "RS_E_OilPress_PC1": 0.0, "RS_E_OilPress_PC2": NaN, "RS_E_RPM_PC1": 0.0, "RS_E_RPM_PC2": NaN, "RS_E_WatTemp_PC1": 0.0, "RS_E_WatTemp_PC2": NaN, "RS_T_OilTemp_PC1": 71.0, "RS_T_OilTemp_PC2": NaN, "month": 9}, {"Unnamed: 0": 16714629, "mapped_veh_id": 147, "timestamps_UTC": "2023-09-02 02:56:27", "lat": 51.0396889, "lon": 3.6947073, "RS_E_InAirTemp_PC1": 0.0, "RS_E_InAirTemp_PC2": NaN, "RS_E_OilPress_PC1": 0.0, "RS_E_OilPress_PC2": NaN, "RS_E_RPM_PC1": 0.0, "RS_E_RPM_PC2": NaN, "RS_E_WatTemp_PC1": 0.0, "RS_E_WatTemp_PC2": NaN, "RS_T_OilTemp_PC1": 74.0, "RS_T_OilTemp_PC2": NaN, "month": 9}, {"Unnamed: 0": 975805, "mapped_veh_id": 147, "timestamps_UTC": "2023-09-02 04:47:29", "lat": 51.0396963, "lon": 3.6947079, "RS_E_InAirTemp_PC1": 30.0, "RS_E_InAirTemp_PC2": 30.0, "RS_E_OilPress_PC1": 345.0, "RS_E_OilPress_PC2": 358.0, "RS_E_RPM_PC1": 805.0, "RS_E_RPM_PC2": 798.0, "RS_E_WatTemp_PC1": 65.0, "RS_E_WatTemp_PC2": 63.0, "RS_T_OilTemp_PC1": 59.0, "RS_T_OilTemp_PC2": 60.0, "month": 9}], [{"Unnamed: 0": 14309016, "mapped_veh_id": 147, "timestamps_UTC": "2023-09-02 02:39:23", "lat": 51.0384027, "lon": 3.6995538, "RS_E_InAirTemp_PC1": 37.0, "RS_E_InAirTemp_PC2": 35.0, "RS_E_OilPress_PC1": 317.0, "RS_E_OilPress_PC2": 258.0, "RS_E_RPM_PC1": 961.0, "RS_E_RPM_PC2": 855.0, "RS_E_WatTemp_PC1": 80.0, "RS_E_WatTemp_PC2": 78.0, "RS_T_OilTemp_PC1": 76.0, "RS_T_OilTemp_PC2": 77.0, "month": 9}, {"Unnamed: 0": 15990020, "mapped_veh_id": 147, "timestamps_UTC": "2023-09-02 02:40:24", "lat": 51.0394482, "lon": 3.6959062, "RS_E_InAirTemp_PC1": 37.0, "RS_E_InAirTemp_PC2": 35.0, "RS_E_OilPress_PC1": 244.0, "RS_E_OilPress_PC2": 255.0, "RS_E_RPM_PC1": 786.0, "RS_E_RPM_PC2": 811.0, "RS_E_WatTemp_PC1": 79.0, "RS_E_WatTemp_PC2": 78.0, "RS_T_OilTemp_PC1": 74.0, "RS_T_OilTemp_PC2": 79.0, "month": 9}, {"Unnamed: 0": 6537432, "mapped_veh_id": 147, "timestamps_UTC": "2023-09-02 02:40:54", "lat": 51.0397014, "lon": 3.6947161, "RS_E_InAirTemp_PC1": 37.0, "RS_E_InAirTemp_PC2": 35.0, "RS_E_OilPress_PC1": 124.0, "RS_E_OilPress_PC2": 158.0, "RS_E_RPM_PC1": 229.0, "RS_E_RPM_PC2": 354.0, "RS_E_WatTemp_PC1": 79.0, "RS_E_WatTemp_PC2": 78.0, "RS_T_OilTemp_PC1": 76.0, "RS_T_OilTemp_PC2": 79.0, "month": 9}, {"Unnamed: 0": 11043931, "mapped_veh_id": 147, "timestamps_UTC": "2023-09-02 02:41:27", "lat": 51.0397008, "lon": 3.6947121, "RS_E_InAirTemp_PC1": 42.0, "RS_E_InAirTemp_PC2": 38.0, "RS_E_OilPress_PC1": 6.0, "RS_E_OilPress_PC2": 3.0, "RS_E_RPM_PC1": 0.0, "RS_E_RPM_PC2": 0.0, "RS_E_WatTemp_PC1": 79.0, "RS_E_WatTemp_PC2": 78.0, "RS_T_OilTemp_PC1": 76.0, "RS_T_OilTemp_PC2": 78.0, "month": 9}, {"Unnamed: 0": 15427206, "mapped_veh_id": 147, "timestamps_UTC": "2023-09-02 02:42:26", "lat": 51.0397005, "lon": 3.6947061, "RS_E_InAirTemp_PC1": 48.0, "RS_E_InAirTemp_PC2": 45.0, "RS_E_OilPress_PC1": 3.0, "RS_E_OilPress_PC2": 3.0, "RS_E_RPM_PC1": 0.0, "RS_E_RPM_PC2": 0.0, "RS_E_WatTemp_PC1": 78.0, "RS_E_WatTemp_PC2": 78.0, "RS_T_OilTemp_PC1": 74.0, "RS_T_OilTemp_PC2": 77.0, "month": 9}, {"Unnamed: 0": 14303905, "mapped_veh_id": 147, "timestamps_UTC": "2023-09-02 02:43:27", "lat": 51.0397109, "lon": 3.694703, "RS_E_InAirTemp_PC1": 51.0, "RS_E_InAirTemp_PC2": 48.0, "RS_E_OilPress_PC1": 3.0, "RS_E_OilPress_PC2": 3.0, "RS_E_RPM_PC1": 0.0, "RS_E_RPM_PC2": 0.0, "RS_E_WatTemp_PC1": 0.0, "RS_E_WatTemp_PC2": 77.0, "RS_T_OilTemp_PC1": 74.0, "RS_T_OilTemp_PC2": 77.0, "month": 9}, {"Unnamed: 0": 16966486, "mapped_veh_id": 147, "timestamps_UTC": "2023-09-02 02:44:27", "lat": 51.0397124, "lon": 3.6947162, "RS_E_InAirTemp_PC1": 0.0, "RS_E_InAirTemp_PC2": 50.0, "RS_E_OilPress_PC1": 3.0, "RS_E_OilPress_PC2": 3.0, "RS_E_RPM_PC1": 0.0, "RS_E_RPM_PC2": 0.0, "RS_E_WatTemp_PC1": 0.0, "RS_E_WatTemp_PC2": 77.0, "RS_T_OilTemp_PC1": 74.0, "RS_T_OilTemp_PC2": 76.0, "month": 9}, {"Unnamed: 0": 10041906, "mapped_veh_id": 147, "timestamps_UTC": "2023-09-02 02:45:27", "lat": 51.0397113, "lon": 3.6947235, "RS_E_InAirTemp_PC1": 56.0, "RS_E_InAirTemp_PC2": NaN, "RS_E_OilPress_PC1": 3.0, "RS_E_OilPress_PC2": NaN, "RS_E_RPM_PC1": 0.0, "RS_E_RPM_PC2": NaN, "RS_E_WatTemp_PC1": 77.0, "RS_E_WatTemp_PC2": NaN, "RS_T_OilTemp_PC1": 75.0, "RS_T_OilTemp_PC2": NaN, "month": 9}, {"Unnamed: 0": 289198, "mapped_veh_id": 147, "timestamps_UTC": "2023-09-02 02:46:31", "lat": 51.0397135, "lon": 3.694743, "RS_E_InAirTemp_PC1": 57.0, "RS_E_InAirTemp_PC2": NaN, "RS_E_OilPress_PC1": 3.0, "RS_E_OilPress_PC2": NaN, "RS_E_RPM_PC1": 0.0, "RS_E_RPM_PC2": NaN, "RS_E_WatTemp_PC1": 77.0, "RS_E_WatTemp_PC2": NaN, "RS_T_OilTemp_PC1": 72.0, "RS_T_OilTemp_PC2": NaN, "month": 9}, {"Unnamed: 0": 279294, "mapped_veh_id": 147, "timestamps_UTC": "2023-09-02 02:47:20", "lat": 51.0396993, "lon": 3.6947288, "RS_E_InAirTemp_PC1": 0.0, "RS_E_InAirTemp_PC2": NaN, "RS_E_OilPress_PC1": 0.0, "RS_E_OilPress_PC2": NaN, "RS_E_RPM_PC1": 0.0, "RS_E_RPM_PC2": NaN, "RS_E_WatTemp_PC1": 0.0, "RS_E_WatTemp_PC2": NaN, "RS_T_OilTemp_PC1": 74.0, "RS_T_OilTemp_PC2": NaN, "month": 9}, {"Unnamed: 0": 7667916, "mapped_veh_id": 147, "timestamps_UTC": "2023-09-02 02:48:20", "lat": 51.0397035, "lon": 3.6947181, "RS_E_InAirTemp_PC1": 0.0, "RS_E_InAirTemp_PC2": NaN, "RS_E_OilPress_PC1": 0.0, "RS_E_OilPress_PC2": NaN, "RS_E_RPM_PC1": 0.0, "RS_E_RPM_PC2": NaN, "RS_E_WatTemp_PC1": 0.0, "RS_E_WatTemp_PC2": NaN, "RS_T_OilTemp_PC1": 74.0, "RS_T_OilTemp_PC2": NaN, "month": 9}, {"Unnamed: 0": 13023447, "mapped_veh_id": 147, "timestamps_UTC": "2023-09-02 02:49:21", "lat": 51.0397057, "lon": 3.6947312, "RS_E_InAirTemp_PC1": 0.0, "RS_E_InAirTemp_PC2": NaN, "RS_E_OilPress_PC1": 0.0, "RS_E_OilPress_PC2": NaN, "RS_E_RPM_PC1": 0.0, "RS_E_RPM_PC2": NaN, "RS_E_WatTemp_PC1": 0.0, "RS_E_WatTemp_PC2": NaN, "RS_T_OilTemp_PC1": 72.0, "RS_T_OilTemp_PC2": NaN, "month": 9}, {"Unnamed: 0": 3850164, "mapped_veh_id": 147, "timestamps_UTC": "2023-09-02 02:50:21", "lat": 51.0396965, "lon": 3.6947289, "RS_E_InAirTemp_PC1": 0.0, "RS_E_InAirTemp_PC2": NaN, "RS_E_OilPress_PC1": 0.0, "RS_E_OilPress_PC2": NaN, "RS_E_RPM_PC1": 0.0, "RS_E_RPM_PC2": NaN, "RS_E_WatTemp_PC1": 0.0, "RS_E_WatTemp_PC2": NaN, "RS_T_OilTemp_PC1": 73.0, "RS_T_OilTemp_PC2": NaN, "month": 9}, {"Unnamed: 0": 9069521, "mapped_veh_id": 147, "timestamps_UTC": "2023-09-02 02:51:23", "lat": 51.0396857, "lon": 3.6947373, "RS_E_InAirTemp_PC1": 0.0, "RS_E_InAirTemp_PC2": NaN, "RS_E_OilPress_PC1": 0.0, "RS_E_OilPress_PC2": NaN, "RS_E_RPM_PC1": 0.0, "RS_E_RPM_PC2": NaN, "RS_E_WatTemp_PC1": 0.0, "RS_E_WatTemp_PC2": NaN, "RS_T_OilTemp_PC1": 72.0, "RS_T_OilTemp_PC2": NaN, "month": 9}, {"Unnamed: 0": 269250, "mapped_veh_id": 147, "timestamps_UTC": "2023-09-02 02:52:24", "lat": 51.0396819, "lon": 3.6947411, "RS_E_InAirTemp_PC1": 0.0, "RS_E_InAirTemp_PC2": NaN, "RS_E_OilPress_PC1": 0.0, "RS_E_OilPress_PC2": NaN, "RS_E_RPM_PC1": 0.0, "RS_E_RPM_PC2": NaN, "RS_E_WatTemp_PC1": 0.0, "RS_E_WatTemp_PC2": NaN, "RS_T_OilTemp_PC1": 72.0, "RS_T_OilTemp_PC2": NaN, "month": 9}, {"Unnamed: 0": 284102, "mapped_veh_id": 147, "timestamps_UTC": "2023-09-02 02:53:24", "lat": 51.0396882, "lon": 3.6947241, "RS_E_InAirTemp_PC1": 0.0, "RS_E_InAirTemp_PC2": NaN, "RS_E_OilPress_PC1": 0.0, "RS_E_OilPress_PC2": NaN, "RS_E_RPM_PC1": 0.0, "RS_E_RPM_PC2": NaN, "RS_E_WatTemp_PC1": 0.0, "RS_E_WatTemp_PC2": NaN, "RS_T_OilTemp_PC1": 71.0, "RS_T_OilTemp_PC2": NaN, "month": 9}, {"Unnamed: 0": 14299065, "mapped_veh_id": 147, "timestamps_UTC": "2023-09-02 02:54:24", "lat": 51.0397035, "lon": 3.6946865, "RS_E_InAirTemp_PC1": 0.0, "RS_E_InAirTemp_PC2": NaN, "RS_E_OilPress_PC1": 0.0, "RS_E_OilPress_PC2": NaN, "RS_E_RPM_PC1": 0.0, "RS_E_RPM_PC2": NaN, "RS_E_WatTemp_PC1": 0.0, "RS_E_WatTemp_PC2": NaN, "RS_T_OilTemp_PC1": 72.0, "RS_T_OilTemp_PC2": NaN, "month": 9}, {"Unnamed: 0": 546082, "mapped_veh_id": 147, "timestamps_UTC": "2023-09-02 02:55:24", "lat": 51.0396688, "lon": 3.6947013, "RS_E_InAirTemp_PC1": 0.0, "RS_E_InAirTemp_PC2": NaN, "RS_E_OilPress_PC1": 0.0, "RS_E_OilPress_PC2": NaN, "RS_E_RPM_PC1": 0.0, "RS_E_RPM_PC2": NaN, "RS_E_WatTemp_PC1": 0.0, "RS_E_WatTemp_PC2": NaN, "RS_T_OilTemp_PC1": 71.0, "RS_T_OilTemp_PC2": NaN, "month": 9}, {"Unnamed: 0": 16714629, "mapped_veh_id": 147, "timestamps_UTC": "2023-09-02 02:56:27", "lat": 51.0396889, "lon": 3.6947073, "RS_E_InAirTemp_PC1": 0.0, "RS_E_InAirTemp_PC2": NaN, "RS_E_OilPress_PC1": 0.0, "RS_E_OilPress_PC2": NaN, "RS_E_RPM_PC1": 0.0, "RS_E_RPM_PC2": NaN, "RS_E_WatTemp_PC1": 0.0, "RS_E_WatTemp_PC2": NaN, "RS_T_OilTemp_PC1": 74.0, "RS_T_OilTemp_PC2": NaN, "month": 9}, {"Unnamed: 0": 975805, "mapped_veh_id": 147, "timestamps_UTC": "2023-09-02 04:47:29", "lat": 51.0396963, "lon": 3.6947079, "RS_E_InAirTemp_PC1": 30.0, "RS_E_InAirTemp_PC2": 30.0, "RS_E_OilPress_PC1": 345.0, "RS_E_OilPress_PC2": 358.0, "RS_E_RPM_PC1": 805.0, "RS_E_RPM_PC2": 798.0, "RS_E_WatTemp_PC1": 65.0, "RS_E_WatTemp_PC2": 63.0, "RS_T_OilTemp_PC1": 59.0, "RS_T_OilTemp_PC2": 60.0, "month": 9}, {"Unnamed: 0": 7677943, "mapped_veh_id": 147, "timestamps_UTC": "2023-09-02 04:48:29", "lat": 51.0397199, "lon": 3.6947146, "RS_E_InAirTemp_PC1": 30.0, "RS_E_InAirTemp_PC2": 30.0, "RS_E_OilPress_PC1": 341.0, "RS_E_OilPress_PC2": 348.0, "RS_E_RPM_PC1": 805.0, "RS_E_RPM_PC2": 797.0, "RS_E_WatTemp_PC1": 66.0, "RS_E_WatTemp_PC2": 65.0, "RS_T_OilTemp_PC1": 60.0, "RS_T_OilTemp_PC2": 62.0, "month": 9}], [{"Unnamed: 0": 15990020, "mapped_veh_id": 147, "timestamps_UTC": "2023-09-02 02:40:24", "lat": 51.0394482, "lon": 3.6959062, "RS_E_InAirTemp_PC1": 37.0, "RS_E_InAirTemp_PC2": 35.0, "RS_E_OilPress_PC1": 244.0, "RS_E_OilPress_PC2": 255.0, "RS_E_RPM_PC1": 786.0, "RS_E_RPM_PC2": 811.0, "RS_E_WatTemp_PC1": 79.0, "RS_E_WatTemp_PC2": 78.0, "RS_T_OilTemp_PC1": 74.0, "RS_T_OilTemp_PC2": 79.0, "month": 9}, {"Unnamed: 0": 6537432, "mapped_veh_id": 147, "timestamps_UTC": "2023-09-02 02:40:54", "lat": 51.0397014, "lon": 3.6947161, "RS_E_InAirTemp_PC1": 37.0, "RS_E_InAirTemp_PC2": 35.0, "RS_E_OilPress_PC1": 124.0, "RS_E_OilPress_PC2": 158.0, "RS_E_RPM_PC1": 229.0, "RS_E_RPM_PC2": 354.0, "RS_E_WatTemp_PC1": 79.0, "RS_E_WatTemp_PC2": 78.0, "RS_T_OilTemp_PC1": 76.0, "RS_T_OilTemp_PC2": 79.0, "month": 9}, {"Unnamed: 0": 11043931, "mapped_veh_id": 147, "timestamps_UTC": "2023-09-02 02:41:27", "lat": 51.0397008, "lon": 3.6947121, "RS_E_InAirTemp_PC1": 42.0, "RS_E_InAirTemp_PC2": 38.0, "RS_E_OilPress_PC1": 6.0, "RS_E_OilPress_PC2": 3.0, "RS_E_RPM_PC1": 0.0, "RS_E_RPM_PC2": 0.0, "RS_E_WatTemp_PC1": 79.0, "RS_E_WatTemp_PC2": 78.0, "RS_T_OilTemp_PC1": 76.0, "RS_T_OilTemp_PC2": 78.0, "month": 9}, {"Unnamed: 0": 15427206, "mapped_veh_id": 147, "timestamps_UTC": "2023-09-02 02:42:26", "lat": 51.0397005, "lon": 3.6947061, "RS_E_InAirTemp_PC1": 48.0, "RS_E_InAirTemp_PC2": 45.0, "RS_E_OilPress_PC1": 3.0, "RS_E_OilPress_PC2": 3.0, "RS_E_RPM_PC1": 0.0, "RS_E_RPM_PC2": 0.0, "RS_E_WatTemp_PC1": 78.0, "RS_E_WatTemp_PC2": 78.0, "RS_T_OilTemp_PC1": 74.0, "RS_T_OilTemp_PC2": 77.0, "month": 9}, {"Unnamed: 0": 14303905, "mapped_veh_id": 147, "timestamps_UTC": "2023-09-02 02:43:27", "lat": 51.0397109, "lon": 3.694703, "RS_E_InAirTemp_PC1": 51.0, "RS_E_InAirTemp_PC2": 48.0, "RS_E_OilPress_PC1": 3.0, "RS_E_OilPress_PC2": 3.0, "RS_E_RPM_PC1": 0.0, "RS_E_RPM_PC2": 0.0, "RS_E_WatTemp_PC1": 0.0, "RS_E_WatTemp_PC2": 77.0, "RS_T_OilTemp_PC1": 74.0, "RS_T_OilTemp_PC2": 77.0, "month": 9}, {"Unnamed: 0": 16966486, "mapped_veh_id": 147, "timestamps_UTC": "2023-09-02 02:44:27", "lat": 51.0397124, "lon": 3.6947162, "RS_E_InAirTemp_PC1": 0.0, "RS_E_InAirTemp_PC2": 50.0, "RS_E_OilPress_PC1": 3.0, "RS_E_OilPress_PC2": 3.0, "RS_E_RPM_PC1": 0.0, "RS_E_RPM_PC2": 0.0, "RS_E_WatTemp_PC1": 0.0, "RS_E_WatTemp_PC2": 77.0, "RS_T_OilTemp_PC1": 74.0, "RS_T_OilTemp_PC2": 76.0, "month": 9}, {"Unnamed: 0": 10041906, "mapped_veh_id": 147, "timestamps_UTC": "2023-09-02 02:45:27", "lat": 51.0397113, "lon": 3.6947235, "RS_E_InAirTemp_PC1": 56.0, "RS_E_InAirTemp_PC2": NaN, "RS_E_OilPress_PC1": 3.0, "RS_E_OilPress_PC2": NaN, "RS_E_RPM_PC1": 0.0, "RS_E_RPM_PC2": NaN, "RS_E_WatTemp_PC1": 77.0, "RS_E_WatTemp_PC2": NaN, "RS_T_OilTemp_PC1": 75.0, "RS_T_OilTemp_PC2": NaN, "month": 9}, {"Unnamed: 0": 289198, "mapped_veh_id": 147, "timestamps_UTC": "2023-09-02 02:46:31", "lat": 51.0397135, "lon": 3.694743, "RS_E_InAirTemp_PC1": 57.0, "RS_E_InAirTemp_PC2": NaN, "RS_E_OilPress_PC1": 3.0, "RS_E_OilPress_PC2": NaN, "RS_E_RPM_PC1": 0.0, "RS_E_RPM_PC2": NaN, "RS_E_WatTemp_PC1": 77.0, "RS_E_WatTemp_PC2": NaN, "RS_T_OilTemp_PC1": 72.0, "RS_T_OilTemp_PC2": NaN, "month": 9}, {"Unnamed: 0": 279294, "mapped_veh_id": 147, "timestamps_UTC": "2023-09-02 02:47:20", "lat": 51.0396993, "lon": 3.6947288, "RS_E_InAirTemp_PC1": 0.0, "RS_E_InAirTemp_PC2": NaN, "RS_E_OilPress_PC1": 0.0, "RS_E_OilPress_PC2": NaN, "RS_E_RPM_PC1": 0.0, "RS_E_RPM_PC2": NaN, "RS_E_WatTemp_PC1": 0.0, "RS_E_WatTemp_PC2": NaN, "RS_T_OilTemp_PC1": 74.0, "RS_T_OilTemp_PC2": NaN, "month": 9}, {"Unnamed: 0": 7667916, "mapped_veh_id": 147, "timestamps_UTC": "2023-09-02 02:48:20", "lat": 51.0397035, "lon": 3.6947181, "RS_E_InAirTemp_PC1": 0.0, "RS_E_InAirTemp_PC2": NaN, "RS_E_OilPress_PC1": 0.0, "RS_E_OilPress_PC2": NaN, "RS_E_RPM_PC1": 0.0, "RS_E_RPM_PC2": NaN, "RS_E_WatTemp_PC1": 0.0, "RS_E_WatTemp_PC2": NaN, "RS_T_OilTemp_PC1": 74.0, "RS_T_OilTemp_PC2": NaN, "month": 9}, {"Unnamed: 0": 13023447, "mapped_veh_id": 147, "timestamps_UTC": "2023-09-02 02:49:21", "lat": 51.0397057, "lon": 3.6947312, "RS_E_InAirTemp_PC1": 0.0, "RS_E_InAirTemp_PC2": NaN, "RS_E_OilPress_PC1": 0.0, "RS_E_OilPress_PC2": NaN, "RS_E_RPM_PC1": 0.0, "RS_E_RPM_PC2": NaN, "RS_E_WatTemp_PC1": 0.0, "RS_E_WatTemp_PC2": NaN, "RS_T_OilTemp_PC1": 72.0, "RS_T_OilTemp_PC2": NaN, "month": 9}, {"Unnamed: 0": 3850164, "mapped_veh_id": 147, "timestamps_UTC": "2023-09-02 02:50:21", "lat": 51.0396965, "lon": 3.6947289, "RS_E_InAirTemp_PC1": 0.0, "RS_E_InAirTemp_PC2": NaN, "RS_E_OilPress_PC1": 0.0, "RS_E_OilPress_PC2": NaN, "RS_E_RPM_PC1": 0.0, "RS_E_RPM_PC2": NaN, "RS_E_WatTemp_PC1": 0.0, "RS_E_WatTemp_PC2": NaN, "RS_T_OilTemp_PC1": 73.0, "RS_T_OilTemp_PC2": NaN, "month": 9}, {"Unnamed: 0": 9069521, "mapped_veh_id": 147, "timestamps_UTC": "2023-09-02 02:51:23", "lat": 51.0396857, "lon": 3.6947373, "RS_E_InAirTemp_PC1": 0.0, "RS_E_InAirTemp_PC2": NaN, "RS_E_OilPress_PC1": 0.0, "RS_E_OilPress_PC2": NaN, "RS_E_RPM_PC1": 0.0, "RS_E_RPM_PC2": NaN, "RS_E_WatTemp_PC1": 0.0, "RS_E_WatTemp_PC2": NaN, "RS_T_OilTemp_PC1": 72.0, "RS_T_OilTemp_PC2": NaN, "month": 9}, {"Unnamed: 0": 269250, "mapped_veh_id": 147, "timestamps_UTC": "2023-09-02 02:52:24", "lat": 51.0396819, "lon": 3.6947411, "RS_E_InAirTemp_PC1": 0.0, "RS_E_InAirTemp_PC2": NaN, "RS_E_OilPress_PC1": 0.0, "RS_E_OilPress_PC2": NaN, "RS_E_RPM_PC1": 0.0, "RS_E_RPM_PC2": NaN, "RS_E_WatTemp_PC1": 0.0, "RS_E_WatTemp_PC2": NaN, "RS_T_OilTemp_PC1": 72.0, "RS_T_OilTemp_PC2": NaN, "month": 9}, {"Unnamed: 0": 284102, "mapped_veh_id": 147, "timestamps_UTC": "2023-09-02 02:53:24", "lat": 51.0396882, "lon": 3.6947241, "RS_E_InAirTemp_PC1": 0.0, "RS_E_InAirTemp_PC2": NaN, "RS_E_OilPress_PC1": 0.0, "RS_E_OilPress_PC2": NaN, "RS_E_RPM_PC1": 0.0, "RS_E_RPM_PC2": NaN, "RS_E_WatTemp_PC1": 0.0, "RS_E_WatTemp_PC2": NaN, "RS_T_OilTemp_PC1": 71.0, "RS_T_OilTemp_PC2": NaN, "month": 9}, {"Unnamed: 0": 14299065, "mapped_veh_id": 147, "timestamps_UTC": "2023-09-02 02:54:24", "lat": 51.0397035, "lon": 3.6946865, "RS_E_InAirTemp_PC1": 0.0, "RS_E_InAirTemp_PC2": NaN, "RS_E_OilPress_PC1": 0.0, "RS_E_OilPress_PC2": NaN, "RS_E_RPM_PC1": 0.0, "RS_E_RPM_PC2": NaN, "RS_E_WatTemp_PC1": 0.0, "RS_E_WatTemp_PC2": NaN, "RS_T_OilTemp_PC1": 72.0, "RS_T_OilTemp_PC2": NaN, "month": 9}, {"Unnamed: 0": 546082, "mapped_veh_id": 147, "timestamps_UTC": "2023-09-02 02:55:24", "lat": 51.0396688, "lon": 3.6947013, "RS_E_InAirTemp_PC1": 0.0, "RS_E_InAirTemp_PC2": NaN, "RS_E_OilPress_PC1": 0.0, "RS_E_OilPress_PC2": NaN, "RS_E_RPM_PC1": 0.0, "RS_E_RPM_PC2": NaN, "RS_E_WatTemp_PC1": 0.0, "RS_E_WatTemp_PC2": NaN, "RS_T_OilTemp_PC1": 71.0, "RS_T_OilTemp_PC2": NaN, "month": 9}, {"Unnamed: 0": 16714629, "mapped_veh_id": 147, "timestamps_UTC": "2023-09-02 02:56:27", "lat": 51.0396889, "lon": 3.6947073, "RS_E_InAirTemp_PC1": 0.0, "RS_E_InAirTemp_PC2": NaN, "RS_E_OilPress_PC1": 0.0, "RS_E_OilPress_PC2": NaN, "RS_E_RPM_PC1": 0.0, "RS_E_RPM_PC2": NaN, "RS_E_WatTemp_PC1": 0.0, "RS_E_WatTemp_PC2": NaN, "RS_T_OilTemp_PC1": 74.0, "RS_T_OilTemp_PC2": NaN, "month": 9}, {"Unnamed: 0": 975805, "mapped_veh_id": 147, "timestamps_UTC": "2023-09-02 04:47:29", "lat": 51.0396963, "lon": 3.6947079, "RS_E_InAirTemp_PC1": 30.0, "RS_E_InAirTemp_PC2": 30.0, "RS_E_OilPress_PC1": 345.0, "RS_E_OilPress_PC2": 358.0, "RS_E_RPM_PC1": 805.0, "RS_E_RPM_PC2": 798.0, "RS_E_WatTemp_PC1": 65.0, "RS_E_WatTemp_PC2": 63.0, "RS_T_OilTemp_PC1": 59.0, "RS_T_OilTemp_PC2": 60.0, "month": 9}, {"Unnamed: 0": 7677943, "mapped_veh_id": 147, "timestamps_UTC": "2023-09-02 04:48:29", "lat": 51.0397199, "lon": 3.6947146, "RS_E_InAirTemp_PC1": 30.0, "RS_E_InAirTemp_PC2": 30.0, "RS_E_OilPress_PC1": 341.0, "RS_E_OilPress_PC2": 348.0, "RS_E_RPM_PC1": 805.0, "RS_E_RPM_PC2": 797.0, "RS_E_WatTemp_PC1": 66.0, "RS_E_WatTemp_PC2": 65.0, "RS_T_OilTemp_PC1": 60.0, "RS_T_OilTemp_PC2": 62.0, "month": 9}, {"Unnamed: 0": 9578842, "mapped_veh_id": 147, "timestamps_UTC": "2023-09-02 04:49:28", "lat": 51.0397194, "lon": 3.6947055, "RS_E_InAirTemp_PC1": 30.0, "RS_E_InAirTemp_PC2": 30.0, "RS_E_OilPress_PC1": 338.0, "RS_E_OilPress_PC2": 334.0, "RS_E_RPM_PC1": 805.0, "RS_E_RPM_PC2": 802.0, "RS_E_WatTemp_PC1": 67.0, "RS_E_WatTemp_PC2": 66.0, "RS_T_OilTemp_PC1": 59.0, "RS_T_OilTemp_PC2": 63.0, "month": 9}], [{"Unnamed: 0": 6537432, "mapped_veh_id": 147, "timestamps_UTC": "2023-09-02 02:40:54", "lat": 51.0397014, "lon": 3.6947161, "RS_E_InAirTemp_PC1": 37.0, "RS_E_InAirTemp_PC2": 35.0, "RS_E_OilPress_PC1": 124.0, "RS_E_OilPress_PC2": 158.0, "RS_E_RPM_PC1": 229.0, "RS_E_RPM_PC2": 354.0, "RS_E_WatTemp_PC1": 79.0, "RS_E_WatTemp_PC2": 78.0, "RS_T_OilTemp_PC1": 76.0, "RS_T_OilTemp_PC2": 79.0, "month": 9}, {"Unnamed: 0": 11043931, "mapped_veh_id": 147, "timestamps_UTC": "2023-09-02 02:41:27", "lat": 51.0397008, "lon": 3.6947121, "RS_E_InAirTemp_PC1": 42.0, "RS_E_InAirTemp_PC2": 38.0, "RS_E_OilPress_PC1": 6.0, "RS_E_OilPress_PC2": 3.0, "RS_E_RPM_PC1": 0.0, "RS_E_RPM_PC2": 0.0, "RS_E_WatTemp_PC1": 79.0, "RS_E_WatTemp_PC2": 78.0, "RS_T_OilTemp_PC1": 76.0, "RS_T_OilTemp_PC2": 78.0, "month": 9}, {"Unnamed: 0": 15427206, "mapped_veh_id": 147, "timestamps_UTC": "2023-09-02 02:42:26", "lat": 51.0397005, "lon": 3.6947061, "RS_E_InAirTemp_PC1": 48.0, "RS_E_InAirTemp_PC2": 45.0, "RS_E_OilPress_PC1": 3.0, "RS_E_OilPress_PC2": 3.0, "RS_E_RPM_PC1": 0.0, "RS_E_RPM_PC2": 0.0, "RS_E_WatTemp_PC1": 78.0, "RS_E_WatTemp_PC2": 78.0, "RS_T_OilTemp_PC1": 74.0, "RS_T_OilTemp_PC2": 77.0, "month": 9}, {"Unnamed: 0": 14303905, "mapped_veh_id": 147, "timestamps_UTC": "2023-09-02 02:43:27", "lat": 51.0397109, "lon": 3.694703, "RS_E_InAirTemp_PC1": 51.0, "RS_E_InAirTemp_PC2": 48.0, "RS_E_OilPress_PC1": 3.0, "RS_E_OilPress_PC2": 3.0, "RS_E_RPM_PC1": 0.0, "RS_E_RPM_PC2": 0.0, "RS_E_WatTemp_PC1": 0.0, "RS_E_WatTemp_PC2": 77.0, "RS_T_OilTemp_PC1": 74.0, "RS_T_OilTemp_PC2": 77.0, "month": 9}, {"Unnamed: 0": 16966486, "mapped_veh_id": 147, "timestamps_UTC": "2023-09-02 02:44:27", "lat": 51.0397124, "lon": 3.6947162, "RS_E_InAirTemp_PC1": 0.0, "RS_E_InAirTemp_PC2": 50.0, "RS_E_OilPress_PC1": 3.0, "RS_E_OilPress_PC2": 3.0, "RS_E_RPM_PC1": 0.0, "RS_E_RPM_PC2": 0.0, "RS_E_WatTemp_PC1": 0.0, "RS_E_WatTemp_PC2": 77.0, "RS_T_OilTemp_PC1": 74.0, "RS_T_OilTemp_PC2": 76.0, "month": 9}, {"Unnamed: 0": 10041906, "mapped_veh_id": 147, "timestamps_UTC": "2023-09-02 02:45:27", "lat": 51.0397113, "lon": 3.6947235, "RS_E_InAirTemp_PC1": 56.0, "RS_E_InAirTemp_PC2": NaN, "RS_E_OilPress_PC1": 3.0, "RS_E_OilPress_PC2": NaN, "RS_E_RPM_PC1": 0.0, "RS_E_RPM_PC2": NaN, "RS_E_WatTemp_PC1": 77.0, "RS_E_WatTemp_PC2": NaN, "RS_T_OilTemp_PC1": 75.0, "RS_T_OilTemp_PC2": NaN, "month": 9}, {"Unnamed: 0": 289198, "mapped_veh_id": 147, "timestamps_UTC": "2023-09-02 02:46:31", "lat": 51.0397135, "lon": 3.694743, "RS_E_InAirTemp_PC1": 57.0, "RS_E_InAirTemp_PC2": NaN, "RS_E_OilPress_PC1": 3.0, "RS_E_OilPress_PC2": NaN, "RS_E_RPM_PC1": 0.0, "RS_E_RPM_PC2": NaN, "RS_E_WatTemp_PC1": 77.0, "RS_E_WatTemp_PC2": NaN, "RS_T_OilTemp_PC1": 72.0, "RS_T_OilTemp_PC2": NaN, "month": 9}, {"Unnamed: 0": 279294, "mapped_veh_id": 147, "timestamps_UTC": "2023-09-02 02:47:20", "lat": 51.0396993, "lon": 3.6947288, "RS_E_InAirTemp_PC1": 0.0, "RS_E_InAirTemp_PC2": NaN, "RS_E_OilPress_PC1": 0.0, "RS_E_OilPress_PC2": NaN, "RS_E_RPM_PC1": 0.0, "RS_E_RPM_PC2": NaN, "RS_E_WatTemp_PC1": 0.0, "RS_E_WatTemp_PC2": NaN, "RS_T_OilTemp_PC1": 74.0, "RS_T_OilTemp_PC2": NaN, "month": 9}, {"Unnamed: 0": 7667916, "mapped_veh_id": 147, "timestamps_UTC": "2023-09-02 02:48:20", "lat": 51.0397035, "lon": 3.6947181, "RS_E_InAirTemp_PC1": 0.0, "RS_E_InAirTemp_PC2": NaN, "RS_E_OilPress_PC1": 0.0, "RS_E_OilPress_PC2": NaN, "RS_E_RPM_PC1": 0.0, "RS_E_RPM_PC2": NaN, "RS_E_WatTemp_PC1": 0.0, "RS_E_WatTemp_PC2": NaN, "RS_T_OilTemp_PC1": 74.0, "RS_T_OilTemp_PC2": NaN, "month": 9}, {"Unnamed: 0": 13023447, "mapped_veh_id": 147, "timestamps_UTC": "2023-09-02 02:49:21", "lat": 51.0397057, "lon": 3.6947312, "RS_E_InAirTemp_PC1": 0.0, "RS_E_InAirTemp_PC2": NaN, "RS_E_OilPress_PC1": 0.0, "RS_E_OilPress_PC2": NaN, "RS_E_RPM_PC1": 0.0, "RS_E_RPM_PC2": NaN, "RS_E_WatTemp_PC1": 0.0, "RS_E_WatTemp_PC2": NaN, "RS_T_OilTemp_PC1": 72.0, "RS_T_OilTemp_PC2": NaN, "month": 9}, {"Unnamed: 0": 3850164, "mapped_veh_id": 147, "timestamps_UTC": "2023-09-02 02:50:21", "lat": 51.0396965, "lon": 3.6947289, "RS_E_InAirTemp_PC1": 0.0, "RS_E_InAirTemp_PC2": NaN, "RS_E_OilPress_PC1": 0.0, "RS_E_OilPress_PC2": NaN, "RS_E_RPM_PC1": 0.0, "RS_E_RPM_PC2": NaN, "RS_E_WatTemp_PC1": 0.0, "RS_E_WatTemp_PC2": NaN, "RS_T_OilTemp_PC1": 73.0, "RS_T_OilTemp_PC2": NaN, "month": 9}, {"Unnamed: 0": 9069521, "mapped_veh_id": 147, "timestamps_UTC": "2023-09-02 02:51:23", "lat": 51.0396857, "lon": 3.6947373, "RS_E_InAirTemp_PC1": 0.0, "RS_E_InAirTemp_PC2": NaN, "RS_E_OilPress_PC1": 0.0, "RS_E_OilPress_PC2": NaN, "RS_E_RPM_PC1": 0.0, "RS_E_RPM_PC2": NaN, "RS_E_WatTemp_PC1": 0.0, "RS_E_WatTemp_PC2": NaN, "RS_T_OilTemp_PC1": 72.0, "RS_T_OilTemp_PC2": NaN, "month": 9}, {"Unnamed: 0": 269250, "mapped_veh_id": 147, "timestamps_UTC": "2023-09-02 02:52:24", "lat": 51.0396819, "lon": 3.6947411, "RS_E_InAirTemp_PC1": 0.0, "RS_E_InAirTemp_PC2": NaN, "RS_E_OilPress_PC1": 0.0, "RS_E_OilPress_PC2": NaN, "RS_E_RPM_PC1": 0.0, "RS_E_RPM_PC2": NaN, "RS_E_WatTemp_PC1": 0.0, "RS_E_WatTemp_PC2": NaN, "RS_T_OilTemp_PC1": 72.0, "RS_T_OilTemp_PC2": NaN, "month": 9}, {"Unnamed: 0": 284102, "mapped_veh_id": 147, "timestamps_UTC": "2023-09-02 02:53:24", "lat": 51.0396882, "lon": 3.6947241, "RS_E_InAirTemp_PC1": 0.0, "RS_E_InAirTemp_PC2": NaN, "RS_E_OilPress_PC1": 0.0, "RS_E_OilPress_PC2": NaN, "RS_E_RPM_PC1": 0.0, "RS_E_RPM_PC2": NaN, "RS_E_WatTemp_PC1": 0.0, "RS_E_WatTemp_PC2": NaN, "RS_T_OilTemp_PC1": 71.0, "RS_T_OilTemp_PC2": NaN, "month": 9}, {"Unnamed: 0": 14299065, "mapped_veh_id": 147, "timestamps_UTC": "2023-09-02 02:54:24", "lat": 51.0397035, "lon": 3.6946865, "RS_E_InAirTemp_PC1": 0.0, "RS_E_InAirTemp_PC2": NaN, "RS_E_OilPress_PC1": 0.0, "RS_E_OilPress_PC2": NaN, "RS_E_RPM_PC1": 0.0, "RS_E_RPM_PC2": NaN, "RS_E_WatTemp_PC1": 0.0, "RS_E_WatTemp_PC2": NaN, "RS_T_OilTemp_PC1": 72.0, "RS_T_OilTemp_PC2": NaN, "month": 9}, {"Unnamed: 0": 546082, "mapped_veh_id": 147, "timestamps_UTC": "2023-09-02 02:55:24", "lat": 51.0396688, "lon": 3.6947013, "RS_E_InAirTemp_PC1": 0.0, "RS_E_InAirTemp_PC2": NaN, "RS_E_OilPress_PC1": 0.0, "RS_E_OilPress_PC2": NaN, "RS_E_RPM_PC1": 0.0, "RS_E_RPM_PC2": NaN, "RS_E_WatTemp_PC1": 0.0, "RS_E_WatTemp_PC2": NaN, "RS_T_OilTemp_PC1": 71.0, "RS_T_OilTemp_PC2": NaN, "month": 9}, {"Unnamed: 0": 16714629, "mapped_veh_id": 147, "timestamps_UTC": "2023-09-02 02:56:27", "lat": 51.0396889, "lon": 3.6947073, "RS_E_InAirTemp_PC1": 0.0, "RS_E_InAirTemp_PC2": NaN, "RS_E_OilPress_PC1": 0.0, "RS_E_OilPress_PC2": NaN, "RS_E_RPM_PC1": 0.0, "RS_E_RPM_PC2": NaN, "RS_E_WatTemp_PC1": 0.0, "RS_E_WatTemp_PC2": NaN, "RS_T_OilTemp_PC1": 74.0, "RS_T_OilTemp_PC2": NaN, "month": 9}, {"Unnamed: 0": 975805, "mapped_veh_id": 147, "timestamps_UTC": "2023-09-02 04:47:29", "lat": 51.0396963, "lon": 3.6947079, "RS_E_InAirTemp_PC1": 30.0, "RS_E_InAirTemp_PC2": 30.0, "RS_E_OilPress_PC1": 345.0, "RS_E_OilPress_PC2": 358.0, "RS_E_RPM_PC1": 805.0, "RS_E_RPM_PC2": 798.0, "RS_E_WatTemp_PC1": 65.0, "RS_E_WatTemp_PC2": 63.0, "RS_T_OilTemp_PC1": 59.0, "RS_T_OilTemp_PC2": 60.0, "month": 9}, {"Unnamed: 0": 7677943, "mapped_veh_id": 147, "timestamps_UTC": "2023-09-02 04:48:29", "lat": 51.0397199, "lon": 3.6947146, "RS_E_InAirTemp_PC1": 30.0, "RS_E_InAirTemp_PC2": 30.0, "RS_E_OilPress_PC1": 341.0, "RS_E_OilPress_PC2": 348.0, "RS_E_RPM_PC1": 805.0, "RS_E_RPM_PC2": 797.0, "RS_E_WatTemp_PC1": 66.0, "RS_E_WatTemp_PC2": 65.0, "RS_T_OilTemp_PC1": 60.0, "RS_T_OilTemp_PC2": 62.0, "month": 9}, {"Unnamed: 0": 9578842, "mapped_veh_id": 147, "timestamps_UTC": "2023-09-02 04:49:28", "lat": 51.0397194, "lon": 3.6947055, "RS_E_InAirTemp_PC1": 30.0, "RS_E_InAirTemp_PC2": 30.0, "RS_E_OilPress_PC1": 338.0, "RS_E_OilPress_PC2": 334.0, "RS_E_RPM_PC1": 805.0, "RS_E_RPM_PC2": 802.0, "RS_E_WatTemp_PC1": 67.0, "RS_E_WatTemp_PC2": 66.0, "RS_T_OilTemp_PC1": 59.0, "RS_T_OilTemp_PC2": 63.0, "month": 9}, {"Unnamed: 0": 7672847, "mapped_veh_id": 147, "timestamps_UTC": "2023-09-02 04:50:28", "lat": 51.0397202, "lon": 3.6947087, "RS_E_InAirTemp_PC1": 30.0, "RS_E_InAirTemp_PC2": 30.0, "RS_E_OilPress_PC1": 327.0, "RS_E_OilPress_PC2": 331.0, "RS_E_RPM_PC1": 807.0, "RS_E_RPM_PC2": 799.0, "RS_E_WatTemp_PC1": 68.0, "RS_E_WatTemp_PC2": 68.0, "RS_T_OilTemp_PC1": 60.0, "RS_T_OilTemp_PC2": 62.0, "month": 9}], [{"Unnamed: 0": 11043931, "mapped_veh_id": 147, "timestamps_UTC": "2023-09-02 02:41:27", "lat": 51.0397008, "lon": 3.6947121, "RS_E_InAirTemp_PC1": 42.0, "RS_E_InAirTemp_PC2": 38.0, "RS_E_OilPress_PC1": 6.0, "RS_E_OilPress_PC2": 3.0, "RS_E_RPM_PC1": 0.0, "RS_E_RPM_PC2": 0.0, "RS_E_WatTemp_PC1": 79.0, "RS_E_WatTemp_PC2": 78.0, "RS_T_OilTemp_PC1": 76.0, "RS_T_OilTemp_PC2": 78.0, "month": 9}, {"Unnamed: 0": 15427206, "mapped_veh_id": 147, "timestamps_UTC": "2023-09-02 02:42:26", "lat": 51.0397005, "lon": 3.6947061, "RS_E_InAirTemp_PC1": 48.0, "RS_E_InAirTemp_PC2": 45.0, "RS_E_OilPress_PC1": 3.0, "RS_E_OilPress_PC2": 3.0, "RS_E_RPM_PC1": 0.0, "RS_E_RPM_PC2": 0.0, "RS_E_WatTemp_PC1": 78.0, "RS_E_WatTemp_PC2": 78.0, "RS_T_OilTemp_PC1": 74.0, "RS_T_OilTemp_PC2": 77.0, "month": 9}, {"Unnamed: 0": 14303905, "mapped_veh_id": 147, "timestamps_UTC": "2023-09-02 02:43:27", "lat": 51.0397109, "lon": 3.694703, "RS_E_InAirTemp_PC1": 51.0, "RS_E_InAirTemp_PC2": 48.0, "RS_E_OilPress_PC1": 3.0, "RS_E_OilPress_PC2": 3.0, "RS_E_RPM_PC1": 0.0, "RS_E_RPM_PC2": 0.0, "RS_E_WatTemp_PC1": 0.0, "RS_E_WatTemp_PC2": 77.0, "RS_T_OilTemp_PC1": 74.0, "RS_T_OilTemp_PC2": 77.0, "month": 9}, {"Unnamed: 0": 16966486, "mapped_veh_id": 147, "timestamps_UTC": "2023-09-02 02:44:27", "lat": 51.0397124, "lon": 3.6947162, "RS_E_InAirTemp_PC1": 0.0, "RS_E_InAirTemp_PC2": 50.0, "RS_E_OilPress_PC1": 3.0, "RS_E_OilPress_PC2": 3.0, "RS_E_RPM_PC1": 0.0, "RS_E_RPM_PC2": 0.0, "RS_E_WatTemp_PC1": 0.0, "RS_E_WatTemp_PC2": 77.0, "RS_T_OilTemp_PC1": 74.0, "RS_T_OilTemp_PC2": 76.0, "month": 9}, {"Unnamed: 0": 10041906, "mapped_veh_id": 147, "timestamps_UTC": "2023-09-02 02:45:27", "lat": 51.0397113, "lon": 3.6947235, "RS_E_InAirTemp_PC1": 56.0, "RS_E_InAirTemp_PC2": NaN, "RS_E_OilPress_PC1": 3.0, "RS_E_OilPress_PC2": NaN, "RS_E_RPM_PC1": 0.0, "RS_E_RPM_PC2": NaN, "RS_E_WatTemp_PC1": 77.0, "RS_E_WatTemp_PC2": NaN, "RS_T_OilTemp_PC1": 75.0, "RS_T_OilTemp_PC2": NaN, "month": 9}, {"Unnamed: 0": 289198, "mapped_veh_id": 147, "timestamps_UTC": "2023-09-02 02:46:31", "lat": 51.0397135, "lon": 3.694743, "RS_E_InAirTemp_PC1": 57.0, "RS_E_InAirTemp_PC2": NaN, "RS_E_OilPress_PC1": 3.0, "RS_E_OilPress_PC2": NaN, "RS_E_RPM_PC1": 0.0, "RS_E_RPM_PC2": NaN, "RS_E_WatTemp_PC1": 77.0, "RS_E_WatTemp_PC2": NaN, "RS_T_OilTemp_PC1": 72.0, "RS_T_OilTemp_PC2": NaN, "month": 9}, {"Unnamed: 0": 279294, "mapped_veh_id": 147, "timestamps_UTC": "2023-09-02 02:47:20", "lat": 51.0396993, "lon": 3.6947288, "RS_E_InAirTemp_PC1": 0.0, "RS_E_InAirTemp_PC2": NaN, "RS_E_OilPress_PC1": 0.0, "RS_E_OilPress_PC2": NaN, "RS_E_RPM_PC1": 0.0, "RS_E_RPM_PC2": NaN, "RS_E_WatTemp_PC1": 0.0, "RS_E_WatTemp_PC2": NaN, "RS_T_OilTemp_PC1": 74.0, "RS_T_OilTemp_PC2": NaN, "month": 9}, {"Unnamed: 0": 7667916, "mapped_veh_id": 147, "timestamps_UTC": "2023-09-02 02:48:20", "lat": 51.0397035, "lon": 3.6947181, "RS_E_InAirTemp_PC1": 0.0, "RS_E_InAirTemp_PC2": NaN, "RS_E_OilPress_PC1": 0.0, "RS_E_OilPress_PC2": NaN, "RS_E_RPM_PC1": 0.0, "RS_E_RPM_PC2": NaN, "RS_E_WatTemp_PC1": 0.0, "RS_E_WatTemp_PC2": NaN, "RS_T_OilTemp_PC1": 74.0, "RS_T_OilTemp_PC2": NaN, "month": 9}, {"Unnamed: 0": 13023447, "mapped_veh_id": 147, "timestamps_UTC": "2023-09-02 02:49:21", "lat": 51.0397057, "lon": 3.6947312, "RS_E_InAirTemp_PC1": 0.0, "RS_E_InAirTemp_PC2": NaN, "RS_E_OilPress_PC1": 0.0, "RS_E_OilPress_PC2": NaN, "RS_E_RPM_PC1": 0.0, "RS_E_RPM_PC2": NaN, "RS_E_WatTemp_PC1": 0.0, "RS_E_WatTemp_PC2": NaN, "RS_T_OilTemp_PC1": 72.0, "RS_T_OilTemp_PC2": NaN, "month": 9}, {"Unnamed: 0": 3850164, "mapped_veh_id": 147, "timestamps_UTC": "2023-09-02 02:50:21", "lat": 51.0396965, "lon": 3.6947289, "RS_E_InAirTemp_PC1": 0.0, "RS_E_InAirTemp_PC2": NaN, "RS_E_OilPress_PC1": 0.0, "RS_E_OilPress_PC2": NaN, "RS_E_RPM_PC1": 0.0, "RS_E_RPM_PC2": NaN, "RS_E_WatTemp_PC1": 0.0, "RS_E_WatTemp_PC2": NaN, "RS_T_OilTemp_PC1": 73.0, "RS_T_OilTemp_PC2": NaN, "month": 9}, {"Unnamed: 0": 9069521, "mapped_veh_id": 147, "timestamps_UTC": "2023-09-02 02:51:23", "lat": 51.0396857, "lon": 3.6947373, "RS_E_InAirTemp_PC1": 0.0, "RS_E_InAirTemp_PC2": NaN, "RS_E_OilPress_PC1": 0.0, "RS_E_OilPress_PC2": NaN, "RS_E_RPM_PC1": 0.0, "RS_E_RPM_PC2": NaN, "RS_E_WatTemp_PC1": 0.0, "RS_E_WatTemp_PC2": NaN, "RS_T_OilTemp_PC1": 72.0, "RS_T_OilTemp_PC2": NaN, "month": 9}, {"Unnamed: 0": 269250, "mapped_veh_id": 147, "timestamps_UTC": "2023-09-02 02:52:24", "lat": 51.0396819, "lon": 3.6947411, "RS_E_InAirTemp_PC1": 0.0, "RS_E_InAirTemp_PC2": NaN, "RS_E_OilPress_PC1": 0.0, "RS_E_OilPress_PC2": NaN, "RS_E_RPM_PC1": 0.0, "RS_E_RPM_PC2": NaN, "RS_E_WatTemp_PC1": 0.0, "RS_E_WatTemp_PC2": NaN, "RS_T_OilTemp_PC1": 72.0, "RS_T_OilTemp_PC2": NaN, "month": 9}, {"Unnamed: 0": 284102, "mapped_veh_id": 147, "timestamps_UTC": "2023-09-02 02:53:24", "lat": 51.0396882, "lon": 3.6947241, "RS_E_InAirTemp_PC1": 0.0, "RS_E_InAirTemp_PC2": NaN, "RS_E_OilPress_PC1": 0.0, "RS_E_OilPress_PC2": NaN, "RS_E_RPM_PC1": 0.0, "RS_E_RPM_PC2": NaN, "RS_E_WatTemp_PC1": 0.0, "RS_E_WatTemp_PC2": NaN, "RS_T_OilTemp_PC1": 71.0, "RS_T_OilTemp_PC2": NaN, "month": 9}, {"Unnamed: 0": 14299065, "mapped_veh_id": 147, "timestamps_UTC": "2023-09-02 02:54:24", "lat": 51.0397035, "lon": 3.6946865, "RS_E_InAirTemp_PC1": 0.0, "RS_E_InAirTemp_PC2": NaN, "RS_E_OilPress_PC1": 0.0, "RS_E_OilPress_PC2": NaN, "RS_E_RPM_PC1": 0.0, "RS_E_RPM_PC2": NaN, "RS_E_WatTemp_PC1": 0.0, "RS_E_WatTemp_PC2": NaN, "RS_T_OilTemp_PC1": 72.0, "RS_T_OilTemp_PC2": NaN, "month": 9}, {"Unnamed: 0": 546082, "mapped_veh_id": 147, "timestamps_UTC": "2023-09-02 02:55:24", "lat": 51.0396688, "lon": 3.6947013, "RS_E_InAirTemp_PC1": 0.0, "RS_E_InAirTemp_PC2": NaN, "RS_E_OilPress_PC1": 0.0, "RS_E_OilPress_PC2": NaN, "RS_E_RPM_PC1": 0.0, "RS_E_RPM_PC2": NaN, "RS_E_WatTemp_PC1": 0.0, "RS_E_WatTemp_PC2": NaN, "RS_T_OilTemp_PC1": 71.0, "RS_T_OilTemp_PC2": NaN, "month": 9}, {"Unnamed: 0": 16714629, "mapped_veh_id": 147, "timestamps_UTC": "2023-09-02 02:56:27", "lat": 51.0396889, "lon": 3.6947073, "RS_E_InAirTemp_PC1": 0.0, "RS_E_InAirTemp_PC2": NaN, "RS_E_OilPress_PC1": 0.0, "RS_E_OilPress_PC2": NaN, "RS_E_RPM_PC1": 0.0, "RS_E_RPM_PC2": NaN, "RS_E_WatTemp_PC1": 0.0, "RS_E_WatTemp_PC2": NaN, "RS_T_OilTemp_PC1": 74.0, "RS_T_OilTemp_PC2": NaN, "month": 9}, {"Unnamed: 0": 975805, "mapped_veh_id": 147, "timestamps_UTC": "2023-09-02 04:47:29", "lat": 51.0396963, "lon": 3.6947079, "RS_E_InAirTemp_PC1": 30.0, "RS_E_InAirTemp_PC2": 30.0, "RS_E_OilPress_PC1": 345.0, "RS_E_OilPress_PC2": 358.0, "RS_E_RPM_PC1": 805.0, "RS_E_RPM_PC2": 798.0, "RS_E_WatTemp_PC1": 65.0, "RS_E_WatTemp_PC2": 63.0, "RS_T_OilTemp_PC1": 59.0, "RS_T_OilTemp_PC2": 60.0, "month": 9}, {"Unnamed: 0": 7677943, "mapped_veh_id": 147, "timestamps_UTC": "2023-09-02 04:48:29", "lat": 51.0397199, "lon": 3.6947146, "RS_E_InAirTemp_PC1": 30.0, "RS_E_InAirTemp_PC2": 30.0, "RS_E_OilPress_PC1": 341.0, "RS_E_OilPress_PC2": 348.0, "RS_E_RPM_PC1": 805.0, "RS_E_RPM_PC2": 797.0, "RS_E_WatTemp_PC1": 66.0, "RS_E_WatTemp_PC2": 65.0, "RS_T_OilTemp_PC1": 60.0, "RS_T_OilTemp_PC2": 62.0, "month": 9}, {"Unnamed: 0": 9578842, "mapped_veh_id": 147, "timestamps_UTC": "2023-09-02 04:49:28", "lat": 51.0397194, "lon": 3.6947055, "RS_E_InAirTemp_PC1": 30.0, "RS_E_InAirTemp_PC2": 30.0, "RS_E_OilPress_PC1": 338.0, "RS_E_OilPress_PC2": 334.0, "RS_E_RPM_PC1": 805.0, "RS_E_RPM_PC2": 802.0, "RS_E_WatTemp_PC1": 67.0, "RS_E_WatTemp_PC2": 66.0, "RS_T_OilTemp_PC1": 59.0, "RS_T_OilTemp_PC2": 63.0, "month": 9}, {"Unnamed: 0": 7672847, "mapped_veh_id": 147, "timestamps_UTC": "2023-09-02 04:50:28", "lat": 51.0397202, "lon": 3.6947087, "RS_E_InAirTemp_PC1": 30.0, "RS_E_InAirTemp_PC2": 30.0, "RS_E_OilPress_PC1": 327.0, "RS_E_OilPress_PC2": 331.0, "RS_E_RPM_PC1": 807.0, "RS_E_RPM_PC2": 799.0, "RS_E_WatTemp_PC1": 68.0, "RS_E_WatTemp_PC2": 68.0, "RS_T_OilTemp_PC1": 60.0, "RS_T_OilTemp_PC2": 62.0, "month": 9}, {"Unnamed: 0": 15452126, "mapped_veh_id": 147, "timestamps_UTC": "2023-09-02 04:51:27", "lat": 51.0397034, "lon": 3.6947069, "RS_E_InAirTemp_PC1": 30.0, "RS_E_InAirTemp_PC2": 30.0, "RS_E_OilPress_PC1": 317.0, "RS_E_OilPress_PC2": 327.0, "RS_E_RPM_PC1": 799.0, "RS_E_RPM_PC2": 802.0, "RS_E_WatTemp_PC1": 70.0, "RS_E_WatTemp_PC2": 69.0, "RS_T_OilTemp_PC1": 60.0, "RS_T_OilTemp_PC2": 62.0, "month": 9}], [{"Unnamed: 0": 15427206, "mapped_veh_id": 147, "timestamps_UTC": "2023-09-02 02:42:26", "lat": 51.0397005, "lon": 3.6947061, "RS_E_InAirTemp_PC1": 48.0, "RS_E_InAirTemp_PC2": 45.0, "RS_E_OilPress_PC1": 3.0, "RS_E_OilPress_PC2": 3.0, "RS_E_RPM_PC1": 0.0, "RS_E_RPM_PC2": 0.0, "RS_E_WatTemp_PC1": 78.0, "RS_E_WatTemp_PC2": 78.0, "RS_T_OilTemp_PC1": 74.0, "RS_T_OilTemp_PC2": 77.0, "month": 9}, {"Unnamed: 0": 14303905, "mapped_veh_id": 147, "timestamps_UTC": "2023-09-02 02:43:27", "lat": 51.0397109, "lon": 3.694703, "RS_E_InAirTemp_PC1": 51.0, "RS_E_InAirTemp_PC2": 48.0, "RS_E_OilPress_PC1": 3.0, "RS_E_OilPress_PC2": 3.0, "RS_E_RPM_PC1": 0.0, "RS_E_RPM_PC2": 0.0, "RS_E_WatTemp_PC1": 0.0, "RS_E_WatTemp_PC2": 77.0, "RS_T_OilTemp_PC1": 74.0, "RS_T_OilTemp_PC2": 77.0, "month": 9}, {"Unnamed: 0": 16966486, "mapped_veh_id": 147, "timestamps_UTC": "2023-09-02 02:44:27", "lat": 51.0397124, "lon": 3.6947162, "RS_E_InAirTemp_PC1": 0.0, "RS_E_InAirTemp_PC2": 50.0, "RS_E_OilPress_PC1": 3.0, "RS_E_OilPress_PC2": 3.0, "RS_E_RPM_PC1": 0.0, "RS_E_RPM_PC2": 0.0, "RS_E_WatTemp_PC1": 0.0, "RS_E_WatTemp_PC2": 77.0, "RS_T_OilTemp_PC1": 74.0, "RS_T_OilTemp_PC2": 76.0, "month": 9}, {"Unnamed: 0": 10041906, "mapped_veh_id": 147, "timestamps_UTC": "2023-09-02 02:45:27", "lat": 51.0397113, "lon": 3.6947235, "RS_E_InAirTemp_PC1": 56.0, "RS_E_InAirTemp_PC2": NaN, "RS_E_OilPress_PC1": 3.0, "RS_E_OilPress_PC2": NaN, "RS_E_RPM_PC1": 0.0, "RS_E_RPM_PC2": NaN, "RS_E_WatTemp_PC1": 77.0, "RS_E_WatTemp_PC2": NaN, "RS_T_OilTemp_PC1": 75.0, "RS_T_OilTemp_PC2": NaN, "month": 9}, {"Unnamed: 0": 289198, "mapped_veh_id": 147, "timestamps_UTC": "2023-09-02 02:46:31", "lat": 51.0397135, "lon": 3.694743, "RS_E_InAirTemp_PC1": 57.0, "RS_E_InAirTemp_PC2": NaN, "RS_E_OilPress_PC1": 3.0, "RS_E_OilPress_PC2": NaN, "RS_E_RPM_PC1": 0.0, "RS_E_RPM_PC2": NaN, "RS_E_WatTemp_PC1": 77.0, "RS_E_WatTemp_PC2": NaN, "RS_T_OilTemp_PC1": 72.0, "RS_T_OilTemp_PC2": NaN, "month": 9}, {"Unnamed: 0": 279294, "mapped_veh_id": 147, "timestamps_UTC": "2023-09-02 02:47:20", "lat": 51.0396993, "lon": 3.6947288, "RS_E_InAirTemp_PC1": 0.0, "RS_E_InAirTemp_PC2": NaN, "RS_E_OilPress_PC1": 0.0, "RS_E_OilPress_PC2": NaN, "RS_E_RPM_PC1": 0.0, "RS_E_RPM_PC2": NaN, "RS_E_WatTemp_PC1": 0.0, "RS_E_WatTemp_PC2": NaN, "RS_T_OilTemp_PC1": 74.0, "RS_T_OilTemp_PC2": NaN, "month": 9}, {"Unnamed: 0": 7667916, "mapped_veh_id": 147, "timestamps_UTC": "2023-09-02 02:48:20", "lat": 51.0397035, "lon": 3.6947181, "RS_E_InAirTemp_PC1": 0.0, "RS_E_InAirTemp_PC2": NaN, "RS_E_OilPress_PC1": 0.0, "RS_E_OilPress_PC2": NaN, "RS_E_RPM_PC1": 0.0, "RS_E_RPM_PC2": NaN, "RS_E_WatTemp_PC1": 0.0, "RS_E_WatTemp_PC2": NaN, "RS_T_OilTemp_PC1": 74.0, "RS_T_OilTemp_PC2": NaN, "month": 9}, {"Unnamed: 0": 13023447, "mapped_veh_id": 147, "timestamps_UTC": "2023-09-02 02:49:21", "lat": 51.0397057, "lon": 3.6947312, "RS_E_InAirTemp_PC1": 0.0, "RS_E_InAirTemp_PC2": NaN, "RS_E_OilPress_PC1": 0.0, "RS_E_OilPress_PC2": NaN, "RS_E_RPM_PC1": 0.0, "RS_E_RPM_PC2": NaN, "RS_E_WatTemp_PC1": 0.0, "RS_E_WatTemp_PC2": NaN, "RS_T_OilTemp_PC1": 72.0, "RS_T_OilTemp_PC2": NaN, "month": 9}, {"Unnamed: 0": 3850164, "mapped_veh_id": 147, "timestamps_UTC": "2023-09-02 02:50:21", "lat": 51.0396965, "lon": 3.6947289, "RS_E_InAirTemp_PC1": 0.0, "RS_E_InAirTemp_PC2": NaN, "RS_E_OilPress_PC1": 0.0, "RS_E_OilPress_PC2": NaN, "RS_E_RPM_PC1": 0.0, "RS_E_RPM_PC2": NaN, "RS_E_WatTemp_PC1": 0.0, "RS_E_WatTemp_PC2": NaN, "RS_T_OilTemp_PC1": 73.0, "RS_T_OilTemp_PC2": NaN, "month": 9}, {"Unnamed: 0": 9069521, "mapped_veh_id": 147, "timestamps_UTC": "2023-09-02 02:51:23", "lat": 51.0396857, "lon": 3.6947373, "RS_E_InAirTemp_PC1": 0.0, "RS_E_InAirTemp_PC2": NaN, "RS_E_OilPress_PC1": 0.0, "RS_E_OilPress_PC2": NaN, "RS_E_RPM_PC1": 0.0, "RS_E_RPM_PC2": NaN, "RS_E_WatTemp_PC1": 0.0, "RS_E_WatTemp_PC2": NaN, "RS_T_OilTemp_PC1": 72.0, "RS_T_OilTemp_PC2": NaN, "month": 9}, {"Unnamed: 0": 269250, "mapped_veh_id": 147, "timestamps_UTC": "2023-09-02 02:52:24", "lat": 51.0396819, "lon": 3.6947411, "RS_E_InAirTemp_PC1": 0.0, "RS_E_InAirTemp_PC2": NaN, "RS_E_OilPress_PC1": 0.0, "RS_E_OilPress_PC2": NaN, "RS_E_RPM_PC1": 0.0, "RS_E_RPM_PC2": NaN, "RS_E_WatTemp_PC1": 0.0, "RS_E_WatTemp_PC2": NaN, "RS_T_OilTemp_PC1": 72.0, "RS_T_OilTemp_PC2": NaN, "month": 9}, {"Unnamed: 0": 284102, "mapped_veh_id": 147, "timestamps_UTC": "2023-09-02 02:53:24", "lat": 51.0396882, "lon": 3.6947241, "RS_E_InAirTemp_PC1": 0.0, "RS_E_InAirTemp_PC2": NaN, "RS_E_OilPress_PC1": 0.0, "RS_E_OilPress_PC2": NaN, "RS_E_RPM_PC1": 0.0, "RS_E_RPM_PC2": NaN, "RS_E_WatTemp_PC1": 0.0, "RS_E_WatTemp_PC2": NaN, "RS_T_OilTemp_PC1": 71.0, "RS_T_OilTemp_PC2": NaN, "month": 9}, {"Unnamed: 0": 14299065, "mapped_veh_id": 147, "timestamps_UTC": "2023-09-02 02:54:24", "lat": 51.0397035, "lon": 3.6946865, "RS_E_InAirTemp_PC1": 0.0, "RS_E_InAirTemp_PC2": NaN, "RS_E_OilPress_PC1": 0.0, "RS_E_OilPress_PC2": NaN, "RS_E_RPM_PC1": 0.0, "RS_E_RPM_PC2": NaN, "RS_E_WatTemp_PC1": 0.0, "RS_E_WatTemp_PC2": NaN, "RS_T_OilTemp_PC1": 72.0, "RS_T_OilTemp_PC2": NaN, "month": 9}, {"Unnamed: 0": 546082, "mapped_veh_id": 147, "timestamps_UTC": "2023-09-02 02:55:24", "lat": 51.0396688, "lon": 3.6947013, "RS_E_InAirTemp_PC1": 0.0, "RS_E_InAirTemp_PC2": NaN, "RS_E_OilPress_PC1": 0.0, "RS_E_OilPress_PC2": NaN, "RS_E_RPM_PC1": 0.0, "RS_E_RPM_PC2": NaN, "RS_E_WatTemp_PC1": 0.0, "RS_E_WatTemp_PC2": NaN, "RS_T_OilTemp_PC1": 71.0, "RS_T_OilTemp_PC2": NaN, "month": 9}, {"Unnamed: 0": 16714629, "mapped_veh_id": 147, "timestamps_UTC": "2023-09-02 02:56:27", "lat": 51.0396889, "lon": 3.6947073, "RS_E_InAirTemp_PC1": 0.0, "RS_E_InAirTemp_PC2": NaN, "RS_E_OilPress_PC1": 0.0, "RS_E_OilPress_PC2": NaN, "RS_E_RPM_PC1": 0.0, "RS_E_RPM_PC2": NaN, "RS_E_WatTemp_PC1": 0.0, "RS_E_WatTemp_PC2": NaN, "RS_T_OilTemp_PC1": 74.0, "RS_T_OilTemp_PC2": NaN, "month": 9}, {"Unnamed: 0": 975805, "mapped_veh_id": 147, "timestamps_UTC": "2023-09-02 04:47:29", "lat": 51.0396963, "lon": 3.6947079, "RS_E_InAirTemp_PC1": 30.0, "RS_E_InAirTemp_PC2": 30.0, "RS_E_OilPress_PC1": 345.0, "RS_E_OilPress_PC2": 358.0, "RS_E_RPM_PC1": 805.0, "RS_E_RPM_PC2": 798.0, "RS_E_WatTemp_PC1": 65.0, "RS_E_WatTemp_PC2": 63.0, "RS_T_OilTemp_PC1": 59.0, "RS_T_OilTemp_PC2": 60.0, "month": 9}, {"Unnamed: 0": 7677943, "mapped_veh_id": 147, "timestamps_UTC": "2023-09-02 04:48:29", "lat": 51.0397199, "lon": 3.6947146, "RS_E_InAirTemp_PC1": 30.0, "RS_E_InAirTemp_PC2": 30.0, "RS_E_OilPress_PC1": 341.0, "RS_E_OilPress_PC2": 348.0, "RS_E_RPM_PC1": 805.0, "RS_E_RPM_PC2": 797.0, "RS_E_WatTemp_PC1": 66.0, "RS_E_WatTemp_PC2": 65.0, "RS_T_OilTemp_PC1": 60.0, "RS_T_OilTemp_PC2": 62.0, "month": 9}, {"Unnamed: 0": 9578842, "mapped_veh_id": 147, "timestamps_UTC": "2023-09-02 04:49:28", "lat": 51.0397194, "lon": 3.6947055, "RS_E_InAirTemp_PC1": 30.0, "RS_E_InAirTemp_PC2": 30.0, "RS_E_OilPress_PC1": 338.0, "RS_E_OilPress_PC2": 334.0, "RS_E_RPM_PC1": 805.0, "RS_E_RPM_PC2": 802.0, "RS_E_WatTemp_PC1": 67.0, "RS_E_WatTemp_PC2": 66.0, "RS_T_OilTemp_PC1": 59.0, "RS_T_OilTemp_PC2": 63.0, "month": 9}, {"Unnamed: 0": 7672847, "mapped_veh_id": 147, "timestamps_UTC": "2023-09-02 04:50:28", "lat": 51.0397202, "lon": 3.6947087, "RS_E_InAirTemp_PC1": 30.0, "RS_E_InAirTemp_PC2": 30.0, "RS_E_OilPress_PC1": 327.0, "RS_E_OilPress_PC2": 331.0, "RS_E_RPM_PC1": 807.0, "RS_E_RPM_PC2": 799.0, "RS_E_WatTemp_PC1": 68.0, "RS_E_WatTemp_PC2": 68.0, "RS_T_OilTemp_PC1": 60.0, "RS_T_OilTemp_PC2": 62.0, "month": 9}, {"Unnamed: 0": 15452126, "mapped_veh_id": 147, "timestamps_UTC": "2023-09-02 04:51:27", "lat": 51.0397034, "lon": 3.6947069, "RS_E_InAirTemp_PC1": 30.0, "RS_E_InAirTemp_PC2": 30.0, "RS_E_OilPress_PC1": 317.0, "RS_E_OilPress_PC2": 327.0, "RS_E_RPM_PC1": 799.0, "RS_E_RPM_PC2": 802.0, "RS_E_WatTemp_PC1": 70.0, "RS_E_WatTemp_PC2": 69.0, "RS_T_OilTemp_PC1": 60.0, "RS_T_OilTemp_PC2": 62.0, "month": 9}, {"Unnamed: 0": 274190, "mapped_veh_id": 147, "timestamps_UTC": "2023-09-02 04:52:27", "lat": 51.0396863, "lon": 3.6947043, "RS_E_InAirTemp_PC1": 31.0, "RS_E_InAirTemp_PC2": 30.0, "RS_E_OilPress_PC1": 310.0, "RS_E_OilPress_PC2": 313.0, "RS_E_RPM_PC1": 800.0, "RS_E_RPM_PC2": 793.0, "RS_E_WatTemp_PC1": 71.0, "RS_E_WatTemp_PC2": 70.0, "RS_T_OilTemp_PC1": 63.0, "RS_T_OilTemp_PC2": 62.0, "month": 9}], [{"Unnamed: 0": 14303905, "mapped_veh_id": 147, "timestamps_UTC": "2023-09-02 02:43:27", "lat": 51.0397109, "lon": 3.694703, "RS_E_InAirTemp_PC1": 51.0, "RS_E_InAirTemp_PC2": 48.0, "RS_E_OilPress_PC1": 3.0, "RS_E_OilPress_PC2": 3.0, "RS_E_RPM_PC1": 0.0, "RS_E_RPM_PC2": 0.0, "RS_E_WatTemp_PC1": 0.0, "RS_E_WatTemp_PC2": 77.0, "RS_T_OilTemp_PC1": 74.0, "RS_T_OilTemp_PC2": 77.0, "month": 9}, {"Unnamed: 0": 16966486, "mapped_veh_id": 147, "timestamps_UTC": "2023-09-02 02:44:27", "lat": 51.0397124, "lon": 3.6947162, "RS_E_InAirTemp_PC1": 0.0, "RS_E_InAirTemp_PC2": 50.0, "RS_E_OilPress_PC1": 3.0, "RS_E_OilPress_PC2": 3.0, "RS_E_RPM_PC1": 0.0, "RS_E_RPM_PC2": 0.0, "RS_E_WatTemp_PC1": 0.0, "RS_E_WatTemp_PC2": 77.0, "RS_T_OilTemp_PC1": 74.0, "RS_T_OilTemp_PC2": 76.0, "month": 9}, {"Unnamed: 0": 10041906, "mapped_veh_id": 147, "timestamps_UTC": "2023-09-02 02:45:27", "lat": 51.0397113, "lon": 3.6947235, "RS_E_InAirTemp_PC1": 56.0, "RS_E_InAirTemp_PC2": NaN, "RS_E_OilPress_PC1": 3.0, "RS_E_OilPress_PC2": NaN, "RS_E_RPM_PC1": 0.0, "RS_E_RPM_PC2": NaN, "RS_E_WatTemp_PC1": 77.0, "RS_E_WatTemp_PC2": NaN, "RS_T_OilTemp_PC1": 75.0, "RS_T_OilTemp_PC2": NaN, "month": 9}, {"Unnamed: 0": 289198, "mapped_veh_id": 147, "timestamps_UTC": "2023-09-02 02:46:31", "lat": 51.0397135, "lon": 3.694743, "RS_E_InAirTemp_PC1": 57.0, "RS_E_InAirTemp_PC2": NaN, "RS_E_OilPress_PC1": 3.0, "RS_E_OilPress_PC2": NaN, "RS_E_RPM_PC1": 0.0, "RS_E_RPM_PC2": NaN, "RS_E_WatTemp_PC1": 77.0, "RS_E_WatTemp_PC2": NaN, "RS_T_OilTemp_PC1": 72.0, "RS_T_OilTemp_PC2": NaN, "month": 9}, {"Unnamed: 0": 279294, "mapped_veh_id": 147, "timestamps_UTC": "2023-09-02 02:47:20", "lat": 51.0396993, "lon": 3.6947288, "RS_E_InAirTemp_PC1": 0.0, "RS_E_InAirTemp_PC2": NaN, "RS_E_OilPress_PC1": 0.0, "RS_E_OilPress_PC2": NaN, "RS_E_RPM_PC1": 0.0, "RS_E_RPM_PC2": NaN, "RS_E_WatTemp_PC1": 0.0, "RS_E_WatTemp_PC2": NaN, "RS_T_OilTemp_PC1": 74.0, "RS_T_OilTemp_PC2": NaN, "month": 9}, {"Unnamed: 0": 7667916, "mapped_veh_id": 147, "timestamps_UTC": "2023-09-02 02:48:20", "lat": 51.0397035, "lon": 3.6947181, "RS_E_InAirTemp_PC1": 0.0, "RS_E_InAirTemp_PC2": NaN, "RS_E_OilPress_PC1": 0.0, "RS_E_OilPress_PC2": NaN, "RS_E_RPM_PC1": 0.0, "RS_E_RPM_PC2": NaN, "RS_E_WatTemp_PC1": 0.0, "RS_E_WatTemp_PC2": NaN, "RS_T_OilTemp_PC1": 74.0, "RS_T_OilTemp_PC2": NaN, "month": 9}, {"Unnamed: 0": 13023447, "mapped_veh_id": 147, "timestamps_UTC": "2023-09-02 02:49:21", "lat": 51.0397057, "lon": 3.6947312, "RS_E_InAirTemp_PC1": 0.0, "RS_E_InAirTemp_PC2": NaN, "RS_E_OilPress_PC1": 0.0, "RS_E_OilPress_PC2": NaN, "RS_E_RPM_PC1": 0.0, "RS_E_RPM_PC2": NaN, "RS_E_WatTemp_PC1": 0.0, "RS_E_WatTemp_PC2": NaN, "RS_T_OilTemp_PC1": 72.0, "RS_T_OilTemp_PC2": NaN, "month": 9}, {"Unnamed: 0": 3850164, "mapped_veh_id": 147, "timestamps_UTC": "2023-09-02 02:50:21", "lat": 51.0396965, "lon": 3.6947289, "RS_E_InAirTemp_PC1": 0.0, "RS_E_InAirTemp_PC2": NaN, "RS_E_OilPress_PC1": 0.0, "RS_E_OilPress_PC2": NaN, "RS_E_RPM_PC1": 0.0, "RS_E_RPM_PC2": NaN, "RS_E_WatTemp_PC1": 0.0, "RS_E_WatTemp_PC2": NaN, "RS_T_OilTemp_PC1": 73.0, "RS_T_OilTemp_PC2": NaN, "month": 9}, {"Unnamed: 0": 9069521, "mapped_veh_id": 147, "timestamps_UTC": "2023-09-02 02:51:23", "lat": 51.0396857, "lon": 3.6947373, "RS_E_InAirTemp_PC1": 0.0, "RS_E_InAirTemp_PC2": NaN, "RS_E_OilPress_PC1": 0.0, "RS_E_OilPress_PC2": NaN, "RS_E_RPM_PC1": 0.0, "RS_E_RPM_PC2": NaN, "RS_E_WatTemp_PC1": 0.0, "RS_E_WatTemp_PC2": NaN, "RS_T_OilTemp_PC1": 72.0, "RS_T_OilTemp_PC2": NaN, "month": 9}, {"Unnamed: 0": 269250, "mapped_veh_id": 147, "timestamps_UTC": "2023-09-02 02:52:24", "lat": 51.0396819, "lon": 3.6947411, "RS_E_InAirTemp_PC1": 0.0, "RS_E_InAirTemp_PC2": NaN, "RS_E_OilPress_PC1": 0.0, "RS_E_OilPress_PC2": NaN, "RS_E_RPM_PC1": 0.0, "RS_E_RPM_PC2": NaN, "RS_E_WatTemp_PC1": 0.0, "RS_E_WatTemp_PC2": NaN, "RS_T_OilTemp_PC1": 72.0, "RS_T_OilTemp_PC2": NaN, "month": 9}, {"Unnamed: 0": 284102, "mapped_veh_id": 147, "timestamps_UTC": "2023-09-02 02:53:24", "lat": 51.0396882, "lon": 3.6947241, "RS_E_InAirTemp_PC1": 0.0, "RS_E_InAirTemp_PC2": NaN, "RS_E_OilPress_PC1": 0.0, "RS_E_OilPress_PC2": NaN, "RS_E_RPM_PC1": 0.0, "RS_E_RPM_PC2": NaN, "RS_E_WatTemp_PC1": 0.0, "RS_E_WatTemp_PC2": NaN, "RS_T_OilTemp_PC1": 71.0, "RS_T_OilTemp_PC2": NaN, "month": 9}, {"Unnamed: 0": 14299065, "mapped_veh_id": 147, "timestamps_UTC": "2023-09-02 02:54:24", "lat": 51.0397035, "lon": 3.6946865, "RS_E_InAirTemp_PC1": 0.0, "RS_E_InAirTemp_PC2": NaN, "RS_E_OilPress_PC1": 0.0, "RS_E_OilPress_PC2": NaN, "RS_E_RPM_PC1": 0.0, "RS_E_RPM_PC2": NaN, "RS_E_WatTemp_PC1": 0.0, "RS_E_WatTemp_PC2": NaN, "RS_T_OilTemp_PC1": 72.0, "RS_T_OilTemp_PC2": NaN, "month": 9}, {"Unnamed: 0": 546082, "mapped_veh_id": 147, "timestamps_UTC": "2023-09-02 02:55:24", "lat": 51.0396688, "lon": 3.6947013, "RS_E_InAirTemp_PC1": 0.0, "RS_E_InAirTemp_PC2": NaN, "RS_E_OilPress_PC1": 0.0, "RS_E_OilPress_PC2": NaN, "RS_E_RPM_PC1": 0.0, "RS_E_RPM_PC2": NaN, "RS_E_WatTemp_PC1": 0.0, "RS_E_WatTemp_PC2": NaN, "RS_T_OilTemp_PC1": 71.0, "RS_T_OilTemp_PC2": NaN, "month": 9}, {"Unnamed: 0": 16714629, "mapped_veh_id": 147, "timestamps_UTC": "2023-09-02 02:56:27", "lat": 51.0396889, "lon": 3.6947073, "RS_E_InAirTemp_PC1": 0.0, "RS_E_InAirTemp_PC2": NaN, "RS_E_OilPress_PC1": 0.0, "RS_E_OilPress_PC2": NaN, "RS_E_RPM_PC1": 0.0, "RS_E_RPM_PC2": NaN, "RS_E_WatTemp_PC1": 0.0, "RS_E_WatTemp_PC2": NaN, "RS_T_OilTemp_PC1": 74.0, "RS_T_OilTemp_PC2": NaN, "month": 9}, {"Unnamed: 0": 975805, "mapped_veh_id": 147, "timestamps_UTC": "2023-09-02 04:47:29", "lat": 51.0396963, "lon": 3.6947079, "RS_E_InAirTemp_PC1": 30.0, "RS_E_InAirTemp_PC2": 30.0, "RS_E_OilPress_PC1": 345.0, "RS_E_OilPress_PC2": 358.0, "RS_E_RPM_PC1": 805.0, "RS_E_RPM_PC2": 798.0, "RS_E_WatTemp_PC1": 65.0, "RS_E_WatTemp_PC2": 63.0, "RS_T_OilTemp_PC1": 59.0, "RS_T_OilTemp_PC2": 60.0, "month": 9}, {"Unnamed: 0": 7677943, "mapped_veh_id": 147, "timestamps_UTC": "2023-09-02 04:48:29", "lat": 51.0397199, "lon": 3.6947146, "RS_E_InAirTemp_PC1": 30.0, "RS_E_InAirTemp_PC2": 30.0, "RS_E_OilPress_PC1": 341.0, "RS_E_OilPress_PC2": 348.0, "RS_E_RPM_PC1": 805.0, "RS_E_RPM_PC2": 797.0, "RS_E_WatTemp_PC1": 66.0, "RS_E_WatTemp_PC2": 65.0, "RS_T_OilTemp_PC1": 60.0, "RS_T_OilTemp_PC2": 62.0, "month": 9}, {"Unnamed: 0": 9578842, "mapped_veh_id": 147, "timestamps_UTC": "2023-09-02 04:49:28", "lat": 51.0397194, "lon": 3.6947055, "RS_E_InAirTemp_PC1": 30.0, "RS_E_InAirTemp_PC2": 30.0, "RS_E_OilPress_PC1": 338.0, "RS_E_OilPress_PC2": 334.0, "RS_E_RPM_PC1": 805.0, "RS_E_RPM_PC2": 802.0, "RS_E_WatTemp_PC1": 67.0, "RS_E_WatTemp_PC2": 66.0, "RS_T_OilTemp_PC1": 59.0, "RS_T_OilTemp_PC2": 63.0, "month": 9}, {"Unnamed: 0": 7672847, "mapped_veh_id": 147, "timestamps_UTC": "2023-09-02 04:50:28", "lat": 51.0397202, "lon": 3.6947087, "RS_E_InAirTemp_PC1": 30.0, "RS_E_InAirTemp_PC2": 30.0, "RS_E_OilPress_PC1": 327.0, "RS_E_OilPress_PC2": 331.0, "RS_E_RPM_PC1": 807.0, "RS_E_RPM_PC2": 799.0, "RS_E_WatTemp_PC1": 68.0, "RS_E_WatTemp_PC2": 68.0, "RS_T_OilTemp_PC1": 60.0, "RS_T_OilTemp_PC2": 62.0, "month": 9}, {"Unnamed: 0": 15452126, "mapped_veh_id": 147, "timestamps_UTC": "2023-09-02 04:51:27", "lat": 51.0397034, "lon": 3.6947069, "RS_E_InAirTemp_PC1": 30.0, "RS_E_InAirTemp_PC2": 30.0, "RS_E_OilPress_PC1": 317.0, "RS_E_OilPress_PC2": 327.0, "RS_E_RPM_PC1": 799.0, "RS_E_RPM_PC2": 802.0, "RS_E_WatTemp_PC1": 70.0, "RS_E_WatTemp_PC2": 69.0, "RS_T_OilTemp_PC1": 60.0, "RS_T_OilTemp_PC2": 62.0, "month": 9}, {"Unnamed: 0": 274190, "mapped_veh_id": 147, "timestamps_UTC": "2023-09-02 04:52:27", "lat": 51.0396863, "lon": 3.6947043, "RS_E_InAirTemp_PC1": 31.0, "RS_E_InAirTemp_PC2": 30.0, "RS_E_OilPress_PC1": 310.0, "RS_E_OilPress_PC2": 313.0, "RS_E_RPM_PC1": 800.0, "RS_E_RPM_PC2": 793.0, "RS_E_WatTemp_PC1": 71.0, "RS_E_WatTemp_PC2": 70.0, "RS_T_OilTemp_PC1": 63.0, "RS_T_OilTemp_PC2": 62.0, "month": 9}, {"Unnamed: 0": 15974904, "mapped_veh_id": 147, "timestamps_UTC": "2023-09-02 04:53:27", "lat": 51.0397004, "lon": 3.6947018, "RS_E_InAirTemp_PC1": 31.0, "RS_E_InAirTemp_PC2": 31.0, "RS_E_OilPress_PC1": 317.0, "RS_E_OilPress_PC2": 317.0, "RS_E_RPM_PC1": 778.0, "RS_E_RPM_PC2": 799.0, "RS_E_WatTemp_PC1": 71.0, "RS_E_WatTemp_PC2": 71.0, "RS_T_OilTemp_PC1": 62.0, "RS_T_OilTemp_PC2": 63.0, "month": 9}], [{"Unnamed: 0": 16966486, "mapped_veh_id": 147, "timestamps_UTC": "2023-09-02 02:44:27", "lat": 51.0397124, "lon": 3.6947162, "RS_E_InAirTemp_PC1": 0.0, "RS_E_InAirTemp_PC2": 50.0, "RS_E_OilPress_PC1": 3.0, "RS_E_OilPress_PC2": 3.0, "RS_E_RPM_PC1": 0.0, "RS_E_RPM_PC2": 0.0, "RS_E_WatTemp_PC1": 0.0, "RS_E_WatTemp_PC2": 77.0, "RS_T_OilTemp_PC1": 74.0, "RS_T_OilTemp_PC2": 76.0, "month": 9}, {"Unnamed: 0": 10041906, "mapped_veh_id": 147, "timestamps_UTC": "2023-09-02 02:45:27", "lat": 51.0397113, "lon": 3.6947235, "RS_E_InAirTemp_PC1": 56.0, "RS_E_InAirTemp_PC2": NaN, "RS_E_OilPress_PC1": 3.0, "RS_E_OilPress_PC2": NaN, "RS_E_RPM_PC1": 0.0, "RS_E_RPM_PC2": NaN, "RS_E_WatTemp_PC1": 77.0, "RS_E_WatTemp_PC2": NaN, "RS_T_OilTemp_PC1": 75.0, "RS_T_OilTemp_PC2": NaN, "month": 9}, {"Unnamed: 0": 289198, "mapped_veh_id": 147, "timestamps_UTC": "2023-09-02 02:46:31", "lat": 51.0397135, "lon": 3.694743, "RS_E_InAirTemp_PC1": 57.0, "RS_E_InAirTemp_PC2": NaN, "RS_E_OilPress_PC1": 3.0, "RS_E_OilPress_PC2": NaN, "RS_E_RPM_PC1": 0.0, "RS_E_RPM_PC2": NaN, "RS_E_WatTemp_PC1": 77.0, "RS_E_WatTemp_PC2": NaN, "RS_T_OilTemp_PC1": 72.0, "RS_T_OilTemp_PC2": NaN, "month": 9}, {"Unnamed: 0": 279294, "mapped_veh_id": 147, "timestamps_UTC": "2023-09-02 02:47:20", "lat": 51.0396993, "lon": 3.6947288, "RS_E_InAirTemp_PC1": 0.0, "RS_E_InAirTemp_PC2": NaN, "RS_E_OilPress_PC1": 0.0, "RS_E_OilPress_PC2": NaN, "RS_E_RPM_PC1": 0.0, "RS_E_RPM_PC2": NaN, "RS_E_WatTemp_PC1": 0.0, "RS_E_WatTemp_PC2": NaN, "RS_T_OilTemp_PC1": 74.0, "RS_T_OilTemp_PC2": NaN, "month": 9}, {"Unnamed: 0": 7667916, "mapped_veh_id": 147, "timestamps_UTC": "2023-09-02 02:48:20", "lat": 51.0397035, "lon": 3.6947181, "RS_E_InAirTemp_PC1": 0.0, "RS_E_InAirTemp_PC2": NaN, "RS_E_OilPress_PC1": 0.0, "RS_E_OilPress_PC2": NaN, "RS_E_RPM_PC1": 0.0, "RS_E_RPM_PC2": NaN, "RS_E_WatTemp_PC1": 0.0, "RS_E_WatTemp_PC2": NaN, "RS_T_OilTemp_PC1": 74.0, "RS_T_OilTemp_PC2": NaN, "month": 9}, {"Unnamed: 0": 13023447, "mapped_veh_id": 147, "timestamps_UTC": "2023-09-02 02:49:21", "lat": 51.0397057, "lon": 3.6947312, "RS_E_InAirTemp_PC1": 0.0, "RS_E_InAirTemp_PC2": NaN, "RS_E_OilPress_PC1": 0.0, "RS_E_OilPress_PC2": NaN, "RS_E_RPM_PC1": 0.0, "RS_E_RPM_PC2": NaN, "RS_E_WatTemp_PC1": 0.0, "RS_E_WatTemp_PC2": NaN, "RS_T_OilTemp_PC1": 72.0, "RS_T_OilTemp_PC2": NaN, "month": 9}, {"Unnamed: 0": 3850164, "mapped_veh_id": 147, "timestamps_UTC": "2023-09-02 02:50:21", "lat": 51.0396965, "lon": 3.6947289, "RS_E_InAirTemp_PC1": 0.0, "RS_E_InAirTemp_PC2": NaN, "RS_E_OilPress_PC1": 0.0, "RS_E_OilPress_PC2": NaN, "RS_E_RPM_PC1": 0.0, "RS_E_RPM_PC2": NaN, "RS_E_WatTemp_PC1": 0.0, "RS_E_WatTemp_PC2": NaN, "RS_T_OilTemp_PC1": 73.0, "RS_T_OilTemp_PC2": NaN, "month": 9}, {"Unnamed: 0": 9069521, "mapped_veh_id": 147, "timestamps_UTC": "2023-09-02 02:51:23", "lat": 51.0396857, "lon": 3.6947373, "RS_E_InAirTemp_PC1": 0.0, "RS_E_InAirTemp_PC2": NaN, "RS_E_OilPress_PC1": 0.0, "RS_E_OilPress_PC2": NaN, "RS_E_RPM_PC1": 0.0, "RS_E_RPM_PC2": NaN, "RS_E_WatTemp_PC1": 0.0, "RS_E_WatTemp_PC2": NaN, "RS_T_OilTemp_PC1": 72.0, "RS_T_OilTemp_PC2": NaN, "month": 9}, {"Unnamed: 0": 269250, "mapped_veh_id": 147, "timestamps_UTC": "2023-09-02 02:52:24", "lat": 51.0396819, "lon": 3.6947411, "RS_E_InAirTemp_PC1": 0.0, "RS_E_InAirTemp_PC2": NaN, "RS_E_OilPress_PC1": 0.0, "RS_E_OilPress_PC2": NaN, "RS_E_RPM_PC1": 0.0, "RS_E_RPM_PC2": NaN, "RS_E_WatTemp_PC1": 0.0, "RS_E_WatTemp_PC2": NaN, "RS_T_OilTemp_PC1": 72.0, "RS_T_OilTemp_PC2": NaN, "month": 9}, {"Unnamed: 0": 284102, "mapped_veh_id": 147, "timestamps_UTC": "2023-09-02 02:53:24", "lat": 51.0396882, "lon": 3.6947241, "RS_E_InAirTemp_PC1": 0.0, "RS_E_InAirTemp_PC2": NaN, "RS_E_OilPress_PC1": 0.0, "RS_E_OilPress_PC2": NaN, "RS_E_RPM_PC1": 0.0, "RS_E_RPM_PC2": NaN, "RS_E_WatTemp_PC1": 0.0, "RS_E_WatTemp_PC2": NaN, "RS_T_OilTemp_PC1": 71.0, "RS_T_OilTemp_PC2": NaN, "month": 9}, {"Unnamed: 0": 14299065, "mapped_veh_id": 147, "timestamps_UTC": "2023-09-02 02:54:24", "lat": 51.0397035, "lon": 3.6946865, "RS_E_InAirTemp_PC1": 0.0, "RS_E_InAirTemp_PC2": NaN, "RS_E_OilPress_PC1": 0.0, "RS_E_OilPress_PC2": NaN, "RS_E_RPM_PC1": 0.0, "RS_E_RPM_PC2": NaN, "RS_E_WatTemp_PC1": 0.0, "RS_E_WatTemp_PC2": NaN, "RS_T_OilTemp_PC1": 72.0, "RS_T_OilTemp_PC2": NaN, "month": 9}, {"Unnamed: 0": 546082, "mapped_veh_id": 147, "timestamps_UTC": "2023-09-02 02:55:24", "lat": 51.0396688, "lon": 3.6947013, "RS_E_InAirTemp_PC1": 0.0, "RS_E_InAirTemp_PC2": NaN, "RS_E_OilPress_PC1": 0.0, "RS_E_OilPress_PC2": NaN, "RS_E_RPM_PC1": 0.0, "RS_E_RPM_PC2": NaN, "RS_E_WatTemp_PC1": 0.0, "RS_E_WatTemp_PC2": NaN, "RS_T_OilTemp_PC1": 71.0, "RS_T_OilTemp_PC2": NaN, "month": 9}, {"Unnamed: 0": 16714629, "mapped_veh_id": 147, "timestamps_UTC": "2023-09-02 02:56:27", "lat": 51.0396889, "lon": 3.6947073, "RS_E_InAirTemp_PC1": 0.0, "RS_E_InAirTemp_PC2": NaN, "RS_E_OilPress_PC1": 0.0, "RS_E_OilPress_PC2": NaN, "RS_E_RPM_PC1": 0.0, "RS_E_RPM_PC2": NaN, "RS_E_WatTemp_PC1": 0.0, "RS_E_WatTemp_PC2": NaN, "RS_T_OilTemp_PC1": 74.0, "RS_T_OilTemp_PC2": NaN, "month": 9}, {"Unnamed: 0": 975805, "mapped_veh_id": 147, "timestamps_UTC": "2023-09-02 04:47:29", "lat": 51.0396963, "lon": 3.6947079, "RS_E_InAirTemp_PC1": 30.0, "RS_E_InAirTemp_PC2": 30.0, "RS_E_OilPress_PC1": 345.0, "RS_E_OilPress_PC2": 358.0, "RS_E_RPM_PC1": 805.0, "RS_E_RPM_PC2": 798.0, "RS_E_WatTemp_PC1": 65.0, "RS_E_WatTemp_PC2": 63.0, "RS_T_OilTemp_PC1": 59.0, "RS_T_OilTemp_PC2": 60.0, "month": 9}, {"Unnamed: 0": 7677943, "mapped_veh_id": 147, "timestamps_UTC": "2023-09-02 04:48:29", "lat": 51.0397199, "lon": 3.6947146, "RS_E_InAirTemp_PC1": 30.0, "RS_E_InAirTemp_PC2": 30.0, "RS_E_OilPress_PC1": 341.0, "RS_E_OilPress_PC2": 348.0, "RS_E_RPM_PC1": 805.0, "RS_E_RPM_PC2": 797.0, "RS_E_WatTemp_PC1": 66.0, "RS_E_WatTemp_PC2": 65.0, "RS_T_OilTemp_PC1": 60.0, "RS_T_OilTemp_PC2": 62.0, "month": 9}, {"Unnamed: 0": 9578842, "mapped_veh_id": 147, "timestamps_UTC": "2023-09-02 04:49:28", "lat": 51.0397194, "lon": 3.6947055, "RS_E_InAirTemp_PC1": 30.0, "RS_E_InAirTemp_PC2": 30.0, "RS_E_OilPress_PC1": 338.0, "RS_E_OilPress_PC2": 334.0, "RS_E_RPM_PC1": 805.0, "RS_E_RPM_PC2": 802.0, "RS_E_WatTemp_PC1": 67.0, "RS_E_WatTemp_PC2": 66.0, "RS_T_OilTemp_PC1": 59.0, "RS_T_OilTemp_PC2": 63.0, "month": 9}, {"Unnamed: 0": 7672847, "mapped_veh_id": 147, "timestamps_UTC": "2023-09-02 04:50:28", "lat": 51.0397202, "lon": 3.6947087, "RS_E_InAirTemp_PC1": 30.0, "RS_E_InAirTemp_PC2": 30.0, "RS_E_OilPress_PC1": 327.0, "RS_E_OilPress_PC2": 331.0, "RS_E_RPM_PC1": 807.0, "RS_E_RPM_PC2": 799.0, "RS_E_WatTemp_PC1": 68.0, "RS_E_WatTemp_PC2": 68.0, "RS_T_OilTemp_PC1": 60.0, "RS_T_OilTemp_PC2": 62.0, "month": 9}, {"Unnamed: 0": 15452126, "mapped_veh_id": 147, "timestamps_UTC": "2023-09-02 04:51:27", "lat": 51.0397034, "lon": 3.6947069, "RS_E_InAirTemp_PC1": 30.0, "RS_E_InAirTemp_PC2": 30.0, "RS_E_OilPress_PC1": 317.0, "RS_E_OilPress_PC2": 327.0, "RS_E_RPM_PC1": 799.0, "RS_E_RPM_PC2": 802.0, "RS_E_WatTemp_PC1": 70.0, "RS_E_WatTemp_PC2": 69.0, "RS_T_OilTemp_PC1": 60.0, "RS_T_OilTemp_PC2": 62.0, "month": 9}, {"Unnamed: 0": 274190, "mapped_veh_id": 147, "timestamps_UTC": "2023-09-02 04:52:27", "lat": 51.0396863, "lon": 3.6947043, "RS_E_InAirTemp_PC1": 31.0, "RS_E_InAirTemp_PC2": 30.0, "RS_E_OilPress_PC1": 310.0, "RS_E_OilPress_PC2": 313.0, "RS_E_RPM_PC1": 800.0, "RS_E_RPM_PC2": 793.0, "RS_E_WatTemp_PC1": 71.0, "RS_E_WatTemp_PC2": 70.0, "RS_T_OilTemp_PC1": 63.0, "RS_T_OilTemp_PC2": 62.0, "month": 9}, {"Unnamed: 0": 15974904, "mapped_veh_id": 147, "timestamps_UTC": "2023-09-02 04:53:27", "lat": 51.0397004, "lon": 3.6947018, "RS_E_InAirTemp_PC1": 31.0, "RS_E_InAirTemp_PC2": 31.0, "RS_E_OilPress_PC1": 317.0, "RS_E_OilPress_PC2": 317.0, "RS_E_RPM_PC1": 778.0, "RS_E_RPM_PC2": 799.0, "RS_E_WatTemp_PC1": 71.0, "RS_E_WatTemp_PC2": 71.0, "RS_T_OilTemp_PC1": 62.0, "RS_T_OilTemp_PC2": 63.0, "month": 9}, {"Unnamed: 0": 3845291, "mapped_veh_id": 147, "timestamps_UTC": "2023-09-02 04:54:27", "lat": 51.0396842, "lon": 3.6947115, "RS_E_InAirTemp_PC1": 31.0, "RS_E_InAirTemp_PC2": 31.0, "RS_E_OilPress_PC1": 307.0, "RS_E_OilPress_PC2": 310.0, "RS_E_RPM_PC1": 802.0, "RS_E_RPM_PC2": 795.0, "RS_E_WatTemp_PC1": 72.0, "RS_E_WatTemp_PC2": 71.0, "RS_T_OilTemp_PC1": 62.0, "RS_T_OilTemp_PC2": 65.0, "month": 9}], [{"Unnamed: 0": 10041906, "mapped_veh_id": 147, "timestamps_UTC": "2023-09-02 02:45:27", "lat": 51.0397113, "lon": 3.6947235, "RS_E_InAirTemp_PC1": 56.0, "RS_E_InAirTemp_PC2": NaN, "RS_E_OilPress_PC1": 3.0, "RS_E_OilPress_PC2": NaN, "RS_E_RPM_PC1": 0.0, "RS_E_RPM_PC2": NaN, "RS_E_WatTemp_PC1": 77.0, "RS_E_WatTemp_PC2": NaN, "RS_T_OilTemp_PC1": 75.0, "RS_T_OilTemp_PC2": NaN, "month": 9}, {"Unnamed: 0": 289198, "mapped_veh_id": 147, "timestamps_UTC": "2023-09-02 02:46:31", "lat": 51.0397135, "lon": 3.694743, "RS_E_InAirTemp_PC1": 57.0, "RS_E_InAirTemp_PC2": NaN, "RS_E_OilPress_PC1": 3.0, "RS_E_OilPress_PC2": NaN, "RS_E_RPM_PC1": 0.0, "RS_E_RPM_PC2": NaN, "RS_E_WatTemp_PC1": 77.0, "RS_E_WatTemp_PC2": NaN, "RS_T_OilTemp_PC1": 72.0, "RS_T_OilTemp_PC2": NaN, "month": 9}, {"Unnamed: 0": 279294, "mapped_veh_id": 147, "timestamps_UTC": "2023-09-02 02:47:20", "lat": 51.0396993, "lon": 3.6947288, "RS_E_InAirTemp_PC1": 0.0, "RS_E_InAirTemp_PC2": NaN, "RS_E_OilPress_PC1": 0.0, "RS_E_OilPress_PC2": NaN, "RS_E_RPM_PC1": 0.0, "RS_E_RPM_PC2": NaN, "RS_E_WatTemp_PC1": 0.0, "RS_E_WatTemp_PC2": NaN, "RS_T_OilTemp_PC1": 74.0, "RS_T_OilTemp_PC2": NaN, "month": 9}, {"Unnamed: 0": 7667916, "mapped_veh_id": 147, "timestamps_UTC": "2023-09-02 02:48:20", "lat": 51.0397035, "lon": 3.6947181, "RS_E_InAirTemp_PC1": 0.0, "RS_E_InAirTemp_PC2": NaN, "RS_E_OilPress_PC1": 0.0, "RS_E_OilPress_PC2": NaN, "RS_E_RPM_PC1": 0.0, "RS_E_RPM_PC2": NaN, "RS_E_WatTemp_PC1": 0.0, "RS_E_WatTemp_PC2": NaN, "RS_T_OilTemp_PC1": 74.0, "RS_T_OilTemp_PC2": NaN, "month": 9}, {"Unnamed: 0": 13023447, "mapped_veh_id": 147, "timestamps_UTC": "2023-09-02 02:49:21", "lat": 51.0397057, "lon": 3.6947312, "RS_E_InAirTemp_PC1": 0.0, "RS_E_InAirTemp_PC2": NaN, "RS_E_OilPress_PC1": 0.0, "RS_E_OilPress_PC2": NaN, "RS_E_RPM_PC1": 0.0, "RS_E_RPM_PC2": NaN, "RS_E_WatTemp_PC1": 0.0, "RS_E_WatTemp_PC2": NaN, "RS_T_OilTemp_PC1": 72.0, "RS_T_OilTemp_PC2": NaN, "month": 9}, {"Unnamed: 0": 3850164, "mapped_veh_id": 147, "timestamps_UTC": "2023-09-02 02:50:21", "lat": 51.0396965, "lon": 3.6947289, "RS_E_InAirTemp_PC1": 0.0, "RS_E_InAirTemp_PC2": NaN, "RS_E_OilPress_PC1": 0.0, "RS_E_OilPress_PC2": NaN, "RS_E_RPM_PC1": 0.0, "RS_E_RPM_PC2": NaN, "RS_E_WatTemp_PC1": 0.0, "RS_E_WatTemp_PC2": NaN, "RS_T_OilTemp_PC1": 73.0, "RS_T_OilTemp_PC2": NaN, "month": 9}, {"Unnamed: 0": 9069521, "mapped_veh_id": 147, "timestamps_UTC": "2023-09-02 02:51:23", "lat": 51.0396857, "lon": 3.6947373, "RS_E_InAirTemp_PC1": 0.0, "RS_E_InAirTemp_PC2": NaN, "RS_E_OilPress_PC1": 0.0, "RS_E_OilPress_PC2": NaN, "RS_E_RPM_PC1": 0.0, "RS_E_RPM_PC2": NaN, "RS_E_WatTemp_PC1": 0.0, "RS_E_WatTemp_PC2": NaN, "RS_T_OilTemp_PC1": 72.0, "RS_T_OilTemp_PC2": NaN, "month": 9}, {"Unnamed: 0": 269250, "mapped_veh_id": 147, "timestamps_UTC": "2023-09-02 02:52:24", "lat": 51.0396819, "lon": 3.6947411, "RS_E_InAirTemp_PC1": 0.0, "RS_E_InAirTemp_PC2": NaN, "RS_E_OilPress_PC1": 0.0, "RS_E_OilPress_PC2": NaN, "RS_E_RPM_PC1": 0.0, "RS_E_RPM_PC2": NaN, "RS_E_WatTemp_PC1": 0.0, "RS_E_WatTemp_PC2": NaN, "RS_T_OilTemp_PC1": 72.0, "RS_T_OilTemp_PC2": NaN, "month": 9}, {"Unnamed: 0": 284102, "mapped_veh_id": 147, "timestamps_UTC": "2023-09-02 02:53:24", "lat": 51.0396882, "lon": 3.6947241, "RS_E_InAirTemp_PC1": 0.0, "RS_E_InAirTemp_PC2": NaN, "RS_E_OilPress_PC1": 0.0, "RS_E_OilPress_PC2": NaN, "RS_E_RPM_PC1": 0.0, "RS_E_RPM_PC2": NaN, "RS_E_WatTemp_PC1": 0.0, "RS_E_WatTemp_PC2": NaN, "RS_T_OilTemp_PC1": 71.0, "RS_T_OilTemp_PC2": NaN, "month": 9}, {"Unnamed: 0": 14299065, "mapped_veh_id": 147, "timestamps_UTC": "2023-09-02 02:54:24", "lat": 51.0397035, "lon": 3.6946865, "RS_E_InAirTemp_PC1": 0.0, "RS_E_InAirTemp_PC2": NaN, "RS_E_OilPress_PC1": 0.0, "RS_E_OilPress_PC2": NaN, "RS_E_RPM_PC1": 0.0, "RS_E_RPM_PC2": NaN, "RS_E_WatTemp_PC1": 0.0, "RS_E_WatTemp_PC2": NaN, "RS_T_OilTemp_PC1": 72.0, "RS_T_OilTemp_PC2": NaN, "month": 9}, {"Unnamed: 0": 546082, "mapped_veh_id": 147, "timestamps_UTC": "2023-09-02 02:55:24", "lat": 51.0396688, "lon": 3.6947013, "RS_E_InAirTemp_PC1": 0.0, "RS_E_InAirTemp_PC2": NaN, "RS_E_OilPress_PC1": 0.0, "RS_E_OilPress_PC2": NaN, "RS_E_RPM_PC1": 0.0, "RS_E_RPM_PC2": NaN, "RS_E_WatTemp_PC1": 0.0, "RS_E_WatTemp_PC2": NaN, "RS_T_OilTemp_PC1": 71.0, "RS_T_OilTemp_PC2": NaN, "month": 9}, {"Unnamed: 0": 16714629, "mapped_veh_id": 147, "timestamps_UTC": "2023-09-02 02:56:27", "lat": 51.0396889, "lon": 3.6947073, "RS_E_InAirTemp_PC1": 0.0, "RS_E_InAirTemp_PC2": NaN, "RS_E_OilPress_PC1": 0.0, "RS_E_OilPress_PC2": NaN, "RS_E_RPM_PC1": 0.0, "RS_E_RPM_PC2": NaN, "RS_E_WatTemp_PC1": 0.0, "RS_E_WatTemp_PC2": NaN, "RS_T_OilTemp_PC1": 74.0, "RS_T_OilTemp_PC2": NaN, "month": 9}, {"Unnamed: 0": 975805, "mapped_veh_id": 147, "timestamps_UTC": "2023-09-02 04:47:29", "lat": 51.0396963, "lon": 3.6947079, "RS_E_InAirTemp_PC1": 30.0, "RS_E_InAirTemp_PC2": 30.0, "RS_E_OilPress_PC1": 345.0, "RS_E_OilPress_PC2": 358.0, "RS_E_RPM_PC1": 805.0, "RS_E_RPM_PC2": 798.0, "RS_E_WatTemp_PC1": 65.0, "RS_E_WatTemp_PC2": 63.0, "RS_T_OilTemp_PC1": 59.0, "RS_T_OilTemp_PC2": 60.0, "month": 9}, {"Unnamed: 0": 7677943, "mapped_veh_id": 147, "timestamps_UTC": "2023-09-02 04:48:29", "lat": 51.0397199, "lon": 3.6947146, "RS_E_InAirTemp_PC1": 30.0, "RS_E_InAirTemp_PC2": 30.0, "RS_E_OilPress_PC1": 341.0, "RS_E_OilPress_PC2": 348.0, "RS_E_RPM_PC1": 805.0, "RS_E_RPM_PC2": 797.0, "RS_E_WatTemp_PC1": 66.0, "RS_E_WatTemp_PC2": 65.0, "RS_T_OilTemp_PC1": 60.0, "RS_T_OilTemp_PC2": 62.0, "month": 9}, {"Unnamed: 0": 9578842, "mapped_veh_id": 147, "timestamps_UTC": "2023-09-02 04:49:28", "lat": 51.0397194, "lon": 3.6947055, "RS_E_InAirTemp_PC1": 30.0, "RS_E_InAirTemp_PC2": 30.0, "RS_E_OilPress_PC1": 338.0, "RS_E_OilPress_PC2": 334.0, "RS_E_RPM_PC1": 805.0, "RS_E_RPM_PC2": 802.0, "RS_E_WatTemp_PC1": 67.0, "RS_E_WatTemp_PC2": 66.0, "RS_T_OilTemp_PC1": 59.0, "RS_T_OilTemp_PC2": 63.0, "month": 9}, {"Unnamed: 0": 7672847, "mapped_veh_id": 147, "timestamps_UTC": "2023-09-02 04:50:28", "lat": 51.0397202, "lon": 3.6947087, "RS_E_InAirTemp_PC1": 30.0, "RS_E_InAirTemp_PC2": 30.0, "RS_E_OilPress_PC1": 327.0, "RS_E_OilPress_PC2": 331.0, "RS_E_RPM_PC1": 807.0, "RS_E_RPM_PC2": 799.0, "RS_E_WatTemp_PC1": 68.0, "RS_E_WatTemp_PC2": 68.0, "RS_T_OilTemp_PC1": 60.0, "RS_T_OilTemp_PC2": 62.0, "month": 9}, {"Unnamed: 0": 15452126, "mapped_veh_id": 147, "timestamps_UTC": "2023-09-02 04:51:27", "lat": 51.0397034, "lon": 3.6947069, "RS_E_InAirTemp_PC1": 30.0, "RS_E_InAirTemp_PC2": 30.0, "RS_E_OilPress_PC1": 317.0, "RS_E_OilPress_PC2": 327.0, "RS_E_RPM_PC1": 799.0, "RS_E_RPM_PC2": 802.0, "RS_E_WatTemp_PC1": 70.0, "RS_E_WatTemp_PC2": 69.0, "RS_T_OilTemp_PC1": 60.0, "RS_T_OilTemp_PC2": 62.0, "month": 9}, {"Unnamed: 0": 274190, "mapped_veh_id": 147, "timestamps_UTC": "2023-09-02 04:52:27", "lat": 51.0396863, "lon": 3.6947043, "RS_E_InAirTemp_PC1": 31.0, "RS_E_InAirTemp_PC2": 30.0, "RS_E_OilPress_PC1": 310.0, "RS_E_OilPress_PC2": 313.0, "RS_E_RPM_PC1": 800.0, "RS_E_RPM_PC2": 793.0, "RS_E_WatTemp_PC1": 71.0, "RS_E_WatTemp_PC2": 70.0, "RS_T_OilTemp_PC1": 63.0, "RS_T_OilTemp_PC2": 62.0, "month": 9}, {"Unnamed: 0": 15974904, "mapped_veh_id": 147, "timestamps_UTC": "2023-09-02 04:53:27", "lat": 51.0397004, "lon": 3.6947018, "RS_E_InAirTemp_PC1": 31.0, "RS_E_InAirTemp_PC2": 31.0, "RS_E_OilPress_PC1": 317.0, "RS_E_OilPress_PC2": 317.0, "RS_E_RPM_PC1": 778.0, "RS_E_RPM_PC2": 799.0, "RS_E_WatTemp_PC1": 71.0, "RS_E_WatTemp_PC2": 71.0, "RS_T_OilTemp_PC1": 62.0, "RS_T_OilTemp_PC2": 63.0, "month": 9}, {"Unnamed: 0": 3845291, "mapped_veh_id": 147, "timestamps_UTC": "2023-09-02 04:54:27", "lat": 51.0396842, "lon": 3.6947115, "RS_E_InAirTemp_PC1": 31.0, "RS_E_InAirTemp_PC2": 31.0, "RS_E_OilPress_PC1": 307.0, "RS_E_OilPress_PC2": 310.0, "RS_E_RPM_PC1": 802.0, "RS_E_RPM_PC2": 795.0, "RS_E_WatTemp_PC1": 72.0, "RS_E_WatTemp_PC2": 71.0, "RS_T_OilTemp_PC1": 62.0, "RS_T_OilTemp_PC2": 65.0, "month": 9}, {"Unnamed: 0": 11592132, "mapped_veh_id": 147, "timestamps_UTC": "2023-09-02 04:55:28", "lat": 51.0397045, "lon": 3.6947207, "RS_E_InAirTemp_PC1": 32.0, "RS_E_InAirTemp_PC2": 31.0, "RS_E_OilPress_PC1": 303.0, "RS_E_OilPress_PC2": 310.0, "RS_E_RPM_PC1": 803.0, "RS_E_RPM_PC2": 802.0, "RS_E_WatTemp_PC1": 73.0, "RS_E_WatTemp_PC2": 72.0, "RS_T_OilTemp_PC1": 64.0, "RS_T_OilTemp_PC2": 65.0, "month": 9}], [{"Unnamed: 0": 289198, "mapped_veh_id": 147, "timestamps_UTC": "2023-09-02 02:46:31", "lat": 51.0397135, "lon": 3.694743, "RS_E_InAirTemp_PC1": 57.0, "RS_E_InAirTemp_PC2": NaN, "RS_E_OilPress_PC1": 3.0, "RS_E_OilPress_PC2": NaN, "RS_E_RPM_PC1": 0.0, "RS_E_RPM_PC2": NaN, "RS_E_WatTemp_PC1": 77.0, "RS_E_WatTemp_PC2": NaN, "RS_T_OilTemp_PC1": 72.0, "RS_T_OilTemp_PC2": NaN, "month": 9}, {"Unnamed: 0": 279294, "mapped_veh_id": 147, "timestamps_UTC": "2023-09-02 02:47:20", "lat": 51.0396993, "lon": 3.6947288, "RS_E_InAirTemp_PC1": 0.0, "RS_E_InAirTemp_PC2": NaN, "RS_E_OilPress_PC1": 0.0, "RS_E_OilPress_PC2": NaN, "RS_E_RPM_PC1": 0.0, "RS_E_RPM_PC2": NaN, "RS_E_WatTemp_PC1": 0.0, "RS_E_WatTemp_PC2": NaN, "RS_T_OilTemp_PC1": 74.0, "RS_T_OilTemp_PC2": NaN, "month": 9}, {"Unnamed: 0": 7667916, "mapped_veh_id": 147, "timestamps_UTC": "2023-09-02 02:48:20", "lat": 51.0397035, "lon": 3.6947181, "RS_E_InAirTemp_PC1": 0.0, "RS_E_InAirTemp_PC2": NaN, "RS_E_OilPress_PC1": 0.0, "RS_E_OilPress_PC2": NaN, "RS_E_RPM_PC1": 0.0, "RS_E_RPM_PC2": NaN, "RS_E_WatTemp_PC1": 0.0, "RS_E_WatTemp_PC2": NaN, "RS_T_OilTemp_PC1": 74.0, "RS_T_OilTemp_PC2": NaN, "month": 9}, {"Unnamed: 0": 13023447, "mapped_veh_id": 147, "timestamps_UTC": "2023-09-02 02:49:21", "lat": 51.0397057, "lon": 3.6947312, "RS_E_InAirTemp_PC1": 0.0, "RS_E_InAirTemp_PC2": NaN, "RS_E_OilPress_PC1": 0.0, "RS_E_OilPress_PC2": NaN, "RS_E_RPM_PC1": 0.0, "RS_E_RPM_PC2": NaN, "RS_E_WatTemp_PC1": 0.0, "RS_E_WatTemp_PC2": NaN, "RS_T_OilTemp_PC1": 72.0, "RS_T_OilTemp_PC2": NaN, "month": 9}, {"Unnamed: 0": 3850164, "mapped_veh_id": 147, "timestamps_UTC": "2023-09-02 02:50:21", "lat": 51.0396965, "lon": 3.6947289, "RS_E_InAirTemp_PC1": 0.0, "RS_E_InAirTemp_PC2": NaN, "RS_E_OilPress_PC1": 0.0, "RS_E_OilPress_PC2": NaN, "RS_E_RPM_PC1": 0.0, "RS_E_RPM_PC2": NaN, "RS_E_WatTemp_PC1": 0.0, "RS_E_WatTemp_PC2": NaN, "RS_T_OilTemp_PC1": 73.0, "RS_T_OilTemp_PC2": NaN, "month": 9}, {"Unnamed: 0": 9069521, "mapped_veh_id": 147, "timestamps_UTC": "2023-09-02 02:51:23", "lat": 51.0396857, "lon": 3.6947373, "RS_E_InAirTemp_PC1": 0.0, "RS_E_InAirTemp_PC2": NaN, "RS_E_OilPress_PC1": 0.0, "RS_E_OilPress_PC2": NaN, "RS_E_RPM_PC1": 0.0, "RS_E_RPM_PC2": NaN, "RS_E_WatTemp_PC1": 0.0, "RS_E_WatTemp_PC2": NaN, "RS_T_OilTemp_PC1": 72.0, "RS_T_OilTemp_PC2": NaN, "month": 9}, {"Unnamed: 0": 269250, "mapped_veh_id": 147, "timestamps_UTC": "2023-09-02 02:52:24", "lat": 51.0396819, "lon": 3.6947411, "RS_E_InAirTemp_PC1": 0.0, "RS_E_InAirTemp_PC2": NaN, "RS_E_OilPress_PC1": 0.0, "RS_E_OilPress_PC2": NaN, "RS_E_RPM_PC1": 0.0, "RS_E_RPM_PC2": NaN, "RS_E_WatTemp_PC1": 0.0, "RS_E_WatTemp_PC2": NaN, "RS_T_OilTemp_PC1": 72.0, "RS_T_OilTemp_PC2": NaN, "month": 9}, {"Unnamed: 0": 284102, "mapped_veh_id": 147, "timestamps_UTC": "2023-09-02 02:53:24", "lat": 51.0396882, "lon": 3.6947241, "RS_E_InAirTemp_PC1": 0.0, "RS_E_InAirTemp_PC2": NaN, "RS_E_OilPress_PC1": 0.0, "RS_E_OilPress_PC2": NaN, "RS_E_RPM_PC1": 0.0, "RS_E_RPM_PC2": NaN, "RS_E_WatTemp_PC1": 0.0, "RS_E_WatTemp_PC2": NaN, "RS_T_OilTemp_PC1": 71.0, "RS_T_OilTemp_PC2": NaN, "month": 9}, {"Unnamed: 0": 14299065, "mapped_veh_id": 147, "timestamps_UTC": "2023-09-02 02:54:24", "lat": 51.0397035, "lon": 3.6946865, "RS_E_InAirTemp_PC1": 0.0, "RS_E_InAirTemp_PC2": NaN, "RS_E_OilPress_PC1": 0.0, "RS_E_OilPress_PC2": NaN, "RS_E_RPM_PC1": 0.0, "RS_E_RPM_PC2": NaN, "RS_E_WatTemp_PC1": 0.0, "RS_E_WatTemp_PC2": NaN, "RS_T_OilTemp_PC1": 72.0, "RS_T_OilTemp_PC2": NaN, "month": 9}, {"Unnamed: 0": 546082, "mapped_veh_id": 147, "timestamps_UTC": "2023-09-02 02:55:24", "lat": 51.0396688, "lon": 3.6947013, "RS_E_InAirTemp_PC1": 0.0, "RS_E_InAirTemp_PC2": NaN, "RS_E_OilPress_PC1": 0.0, "RS_E_OilPress_PC2": NaN, "RS_E_RPM_PC1": 0.0, "RS_E_RPM_PC2": NaN, "RS_E_WatTemp_PC1": 0.0, "RS_E_WatTemp_PC2": NaN, "RS_T_OilTemp_PC1": 71.0, "RS_T_OilTemp_PC2": NaN, "month": 9}, {"Unnamed: 0": 16714629, "mapped_veh_id": 147, "timestamps_UTC": "2023-09-02 02:56:27", "lat": 51.0396889, "lon": 3.6947073, "RS_E_InAirTemp_PC1": 0.0, "RS_E_InAirTemp_PC2": NaN, "RS_E_OilPress_PC1": 0.0, "RS_E_OilPress_PC2": NaN, "RS_E_RPM_PC1": 0.0, "RS_E_RPM_PC2": NaN, "RS_E_WatTemp_PC1": 0.0, "RS_E_WatTemp_PC2": NaN, "RS_T_OilTemp_PC1": 74.0, "RS_T_OilTemp_PC2": NaN, "month": 9}, {"Unnamed: 0": 975805, "mapped_veh_id": 147, "timestamps_UTC": "2023-09-02 04:47:29", "lat": 51.0396963, "lon": 3.6947079, "RS_E_InAirTemp_PC1": 30.0, "RS_E_InAirTemp_PC2": 30.0, "RS_E_OilPress_PC1": 345.0, "RS_E_OilPress_PC2": 358.0, "RS_E_RPM_PC1": 805.0, "RS_E_RPM_PC2": 798.0, "RS_E_WatTemp_PC1": 65.0, "RS_E_WatTemp_PC2": 63.0, "RS_T_OilTemp_PC1": 59.0, "RS_T_OilTemp_PC2": 60.0, "month": 9}, {"Unnamed: 0": 7677943, "mapped_veh_id": 147, "timestamps_UTC": "2023-09-02 04:48:29", "lat": 51.0397199, "lon": 3.6947146, "RS_E_InAirTemp_PC1": 30.0, "RS_E_InAirTemp_PC2": 30.0, "RS_E_OilPress_PC1": 341.0, "RS_E_OilPress_PC2": 348.0, "RS_E_RPM_PC1": 805.0, "RS_E_RPM_PC2": 797.0, "RS_E_WatTemp_PC1": 66.0, "RS_E_WatTemp_PC2": 65.0, "RS_T_OilTemp_PC1": 60.0, "RS_T_OilTemp_PC2": 62.0, "month": 9}, {"Unnamed: 0": 9578842, "mapped_veh_id": 147, "timestamps_UTC": "2023-09-02 04:49:28", "lat": 51.0397194, "lon": 3.6947055, "RS_E_InAirTemp_PC1": 30.0, "RS_E_InAirTemp_PC2": 30.0, "RS_E_OilPress_PC1": 338.0, "RS_E_OilPress_PC2": 334.0, "RS_E_RPM_PC1": 805.0, "RS_E_RPM_PC2": 802.0, "RS_E_WatTemp_PC1": 67.0, "RS_E_WatTemp_PC2": 66.0, "RS_T_OilTemp_PC1": 59.0, "RS_T_OilTemp_PC2": 63.0, "month": 9}, {"Unnamed: 0": 7672847, "mapped_veh_id": 147, "timestamps_UTC": "2023-09-02 04:50:28", "lat": 51.0397202, "lon": 3.6947087, "RS_E_InAirTemp_PC1": 30.0, "RS_E_InAirTemp_PC2": 30.0, "RS_E_OilPress_PC1": 327.0, "RS_E_OilPress_PC2": 331.0, "RS_E_RPM_PC1": 807.0, "RS_E_RPM_PC2": 799.0, "RS_E_WatTemp_PC1": 68.0, "RS_E_WatTemp_PC2": 68.0, "RS_T_OilTemp_PC1": 60.0, "RS_T_OilTemp_PC2": 62.0, "month": 9}, {"Unnamed: 0": 15452126, "mapped_veh_id": 147, "timestamps_UTC": "2023-09-02 04:51:27", "lat": 51.0397034, "lon": 3.6947069, "RS_E_InAirTemp_PC1": 30.0, "RS_E_InAirTemp_PC2": 30.0, "RS_E_OilPress_PC1": 317.0, "RS_E_OilPress_PC2": 327.0, "RS_E_RPM_PC1": 799.0, "RS_E_RPM_PC2": 802.0, "RS_E_WatTemp_PC1": 70.0, "RS_E_WatTemp_PC2": 69.0, "RS_T_OilTemp_PC1": 60.0, "RS_T_OilTemp_PC2": 62.0, "month": 9}, {"Unnamed: 0": 274190, "mapped_veh_id": 147, "timestamps_UTC": "2023-09-02 04:52:27", "lat": 51.0396863, "lon": 3.6947043, "RS_E_InAirTemp_PC1": 31.0, "RS_E_InAirTemp_PC2": 30.0, "RS_E_OilPress_PC1": 310.0, "RS_E_OilPress_PC2": 313.0, "RS_E_RPM_PC1": 800.0, "RS_E_RPM_PC2": 793.0, "RS_E_WatTemp_PC1": 71.0, "RS_E_WatTemp_PC2": 70.0, "RS_T_OilTemp_PC1": 63.0, "RS_T_OilTemp_PC2": 62.0, "month": 9}, {"Unnamed: 0": 15974904, "mapped_veh_id": 147, "timestamps_UTC": "2023-09-02 04:53:27", "lat": 51.0397004, "lon": 3.6947018, "RS_E_InAirTemp_PC1": 31.0, "RS_E_InAirTemp_PC2": 31.0, "RS_E_OilPress_PC1": 317.0, "RS_E_OilPress_PC2": 317.0, "RS_E_RPM_PC1": 778.0, "RS_E_RPM_PC2": 799.0, "RS_E_WatTemp_PC1": 71.0, "RS_E_WatTemp_PC2": 71.0, "RS_T_OilTemp_PC1": 62.0, "RS_T_OilTemp_PC2": 63.0, "month": 9}, {"Unnamed: 0": 3845291, "mapped_veh_id": 147, "timestamps_UTC": "2023-09-02 04:54:27", "lat": 51.0396842, "lon": 3.6947115, "RS_E_InAirTemp_PC1": 31.0, "RS_E_InAirTemp_PC2": 31.0, "RS_E_OilPress_PC1": 307.0, "RS_E_OilPress_PC2": 310.0, "RS_E_RPM_PC1": 802.0, "RS_E_RPM_PC2": 795.0, "RS_E_WatTemp_PC1": 72.0, "RS_E_WatTemp_PC2": 71.0, "RS_T_OilTemp_PC1": 62.0, "RS_T_OilTemp_PC2": 65.0, "month": 9}, {"Unnamed: 0": 11592132, "mapped_veh_id": 147, "timestamps_UTC": "2023-09-02 04:55:28", "lat": 51.0397045, "lon": 3.6947207, "RS_E_InAirTemp_PC1": 32.0, "RS_E_InAirTemp_PC2": 31.0, "RS_E_OilPress_PC1": 303.0, "RS_E_OilPress_PC2": 310.0, "RS_E_RPM_PC1": 803.0, "RS_E_RPM_PC2": 802.0, "RS_E_WatTemp_PC1": 73.0, "RS_E_WatTemp_PC2": 72.0, "RS_T_OilTemp_PC1": 64.0, "RS_T_OilTemp_PC2": 65.0, "month": 9}, {"Unnamed: 0": 12536641, "mapped_veh_id": 147, "timestamps_UTC": "2023-09-02 04:56:30", "lat": 51.039707, "lon": 3.6947222, "RS_E_InAirTemp_PC1": 32.0, "RS_E_InAirTemp_PC2": 31.0, "RS_E_OilPress_PC1": 300.0, "RS_E_OilPress_PC2": 303.0, "RS_E_RPM_PC1": 797.0, "RS_E_RPM_PC2": 791.0, "RS_E_WatTemp_PC1": 73.0, "RS_E_WatTemp_PC2": 72.0, "RS_T_OilTemp_PC1": 66.0, "RS_T_OilTemp_PC2": 65.0, "month": 9}]]}